{
"meta":{"launch_mode":"Train","name":"experiment","iteration_count":1000,"learn_metrics":[{"best_value":"Min","name":"RMSE"}],"test_sets":[],"test_metrics":[],"learn_sets":["learn"]},
"iterations":[
{"learn":[634198.426],"iteration":0,"passed_time":0.05118475023,"remaining_time":51.13356548},
{"learn":[618536.3306],"iteration":1,"passed_time":0.0955919643,"remaining_time":47.70039019},
{"learn":[603456.2159],"iteration":2,"passed_time":0.145427588,"remaining_time":48.33043507},
{"learn":[588796.7727],"iteration":3,"passed_time":0.1955936351,"remaining_time":48.70281514},
{"learn":[575073.8585],"iteration":4,"passed_time":0.2250380441,"remaining_time":44.78257078},
{"learn":[561393.3464],"iteration":5,"passed_time":0.2694291693,"remaining_time":44.63543238},
{"learn":[548096.3841],"iteration":6,"passed_time":0.3158367845,"remaining_time":44.80370385},
{"learn":[535336.2336],"iteration":7,"passed_time":0.3613548005,"remaining_time":44.80799526},
{"learn":[523179.2972],"iteration":8,"passed_time":0.4091986795,"remaining_time":45.05732127},
{"learn":[511092.6406],"iteration":9,"passed_time":0.4530588779,"remaining_time":44.85282891},
{"learn":[499521.9959],"iteration":10,"passed_time":0.4985291721,"remaining_time":44.82230466},
{"learn":[488438.3634],"iteration":11,"passed_time":0.5493382288,"remaining_time":45.22884751},
{"learn":[477596.1244],"iteration":12,"passed_time":0.595023868,"remaining_time":45.1760429},
{"learn":[467142.6669],"iteration":13,"passed_time":0.6396942422,"remaining_time":45.05275163},
{"learn":[457030.0177],"iteration":14,"passed_time":0.6846437475,"remaining_time":44.95827276},
{"learn":[447342.2595],"iteration":15,"passed_time":0.7278321407,"remaining_time":44.76167665},
{"learn":[437905.3596],"iteration":16,"passed_time":0.7714879716,"remaining_time":44.61015742},
{"learn":[428712.6887],"iteration":17,"passed_time":0.8200203069,"remaining_time":44.73666341},
{"learn":[420052.1265],"iteration":18,"passed_time":0.8655449534,"remaining_time":44.68945259},
{"learn":[411587.8038],"iteration":19,"passed_time":0.9096779867,"remaining_time":44.57422135},
{"learn":[403540.3011],"iteration":20,"passed_time":0.9560272794,"remaining_time":44.56908126},
{"learn":[395635.1117],"iteration":21,"passed_time":1.002879086,"remaining_time":44.58253391},
{"learn":[388153.1786],"iteration":22,"passed_time":1.049928683,"remaining_time":44.59914449},
{"learn":[380984.2464],"iteration":23,"passed_time":1.093394769,"remaining_time":44.4647206},
{"learn":[374022.0953],"iteration":24,"passed_time":1.136813136,"remaining_time":44.33571229},
{"learn":[367356.3223],"iteration":25,"passed_time":1.185687531,"remaining_time":44.41767905},
{"learn":[360873.3174],"iteration":26,"passed_time":1.23359597,"remaining_time":44.45514368},
{"learn":[354670.9922],"iteration":27,"passed_time":1.281411579,"remaining_time":44.48328768},
{"learn":[348699.9556],"iteration":28,"passed_time":1.329708272,"remaining_time":44.52230109},
{"learn":[343004.8007],"iteration":29,"passed_time":1.376297507,"remaining_time":44.50028606},
{"learn":[337330.7579],"iteration":30,"passed_time":1.422132579,"remaining_time":44.45311192},
{"learn":[332121.4033],"iteration":31,"passed_time":1.468526557,"remaining_time":44.42292835},
{"learn":[326936.6009],"iteration":32,"passed_time":1.516641843,"remaining_time":44.4422019},
{"learn":[322087.0876],"iteration":33,"passed_time":1.564521579,"remaining_time":44.45081899},
{"learn":[317400.639],"iteration":34,"passed_time":1.609498315,"remaining_time":44.37616783},
{"learn":[312882.9694],"iteration":35,"passed_time":1.653320179,"remaining_time":44.27224035},
{"learn":[308693.1378],"iteration":36,"passed_time":1.699594049,"remaining_time":44.23538025},
{"learn":[304528.4475],"iteration":37,"passed_time":1.745670729,"remaining_time":44.19303266},
{"learn":[300502.3066],"iteration":38,"passed_time":1.793121143,"remaining_time":44.18434407},
{"learn":[296668.0289],"iteration":39,"passed_time":1.836235826,"remaining_time":44.06965984},
{"learn":[293119.7376],"iteration":40,"passed_time":1.880530726,"remaining_time":43.98607234},
{"learn":[289703.3833],"iteration":41,"passed_time":1.926455677,"remaining_time":43.94153662},
{"learn":[286446.2654],"iteration":42,"passed_time":1.976522161,"remaining_time":43.98910948},
{"learn":[283267.6045],"iteration":43,"passed_time":2.02214893,"remaining_time":43.93578131},
{"learn":[280325.4895],"iteration":44,"passed_time":2.068569408,"remaining_time":43.89963965},
{"learn":[277372.2535],"iteration":45,"passed_time":2.1133166,"remaining_time":43.82834862},
{"learn":[274588.8568],"iteration":46,"passed_time":2.158751619,"remaining_time":43.7721339},
{"learn":[271892.955],"iteration":47,"passed_time":2.210058638,"remaining_time":43.83282965},
{"learn":[269358.878],"iteration":48,"passed_time":2.25188888,"remaining_time":43.70502704},
{"learn":[266958.325],"iteration":49,"passed_time":2.299587883,"remaining_time":43.69216978},
{"learn":[264577.2515],"iteration":50,"passed_time":2.344871977,"remaining_time":43.63300992},
{"learn":[262428.7448],"iteration":51,"passed_time":2.383941424,"remaining_time":43.46108597},
{"learn":[260351.0885],"iteration":52,"passed_time":2.43129814,"remaining_time":43.44225167},
{"learn":[258276.0028],"iteration":53,"passed_time":2.480594912,"remaining_time":43.45634791},
{"learn":[256377.6596],"iteration":54,"passed_time":2.516610098,"remaining_time":43.23993714},
{"learn":[254492.538],"iteration":55,"passed_time":2.56374126,"remaining_time":43.21735266},
{"learn":[252779.6716],"iteration":56,"passed_time":2.607257061,"remaining_time":43.13409488},
{"learn":[251047.8269],"iteration":57,"passed_time":2.651513721,"remaining_time":43.0642401},
{"learn":[249391.0802],"iteration":58,"passed_time":2.696771498,"remaining_time":43.01122},
{"learn":[247776.8599],"iteration":59,"passed_time":2.740059061,"remaining_time":42.92759195},
{"learn":[246337.0426],"iteration":60,"passed_time":2.784829848,"remaining_time":42.86811847},
{"learn":[244943.5747],"iteration":61,"passed_time":2.826734799,"remaining_time":42.76576196},
{"learn":[243592.3984],"iteration":62,"passed_time":2.871188745,"remaining_time":42.70323577},
{"learn":[242313.5212],"iteration":63,"passed_time":2.914973156,"remaining_time":42.6314824},
{"learn":[240997.8422],"iteration":64,"passed_time":2.959176411,"remaining_time":42.56661453},
{"learn":[239810.9002],"iteration":65,"passed_time":3.00648229,"remaining_time":42.54627968},
{"learn":[238700.6761],"iteration":66,"passed_time":3.056197559,"remaining_time":42.55869138},
{"learn":[237603.0852],"iteration":67,"passed_time":3.099499526,"remaining_time":42.48137586},
{"learn":[236502.2984],"iteration":68,"passed_time":3.144006806,"remaining_time":42.42130923},
{"learn":[235412.1272],"iteration":69,"passed_time":3.187412442,"remaining_time":42.34705102},
{"learn":[234422.3289],"iteration":70,"passed_time":3.231441809,"remaining_time":42.28182311},
{"learn":[233482.3826],"iteration":71,"passed_time":3.271489223,"remaining_time":42.1658611},
{"learn":[232622.1151],"iteration":72,"passed_time":3.313431653,"remaining_time":42.07604304},
{"learn":[231784.2812],"iteration":73,"passed_time":3.357724958,"remaining_time":42.01693664},
{"learn":[230962.5268],"iteration":74,"passed_time":3.400920678,"remaining_time":41.94468836},
{"learn":[230167.3205],"iteration":75,"passed_time":3.442233646,"remaining_time":41.85031433},
{"learn":[229421.1607],"iteration":76,"passed_time":3.484083097,"remaining_time":41.76374933},
{"learn":[228772.5045],"iteration":77,"passed_time":3.527793214,"remaining_time":41.70032491},
{"learn":[228116.8164],"iteration":78,"passed_time":3.573181021,"remaining_time":41.65695849},
{"learn":[227504.6639],"iteration":79,"passed_time":3.621649452,"remaining_time":41.6489687},
{"learn":[227023.6927],"iteration":80,"passed_time":3.667806359,"remaining_time":41.61375362},
{"learn":[226426.1317],"iteration":81,"passed_time":3.709992827,"remaining_time":41.53382213},
{"learn":[225820.9164],"iteration":82,"passed_time":3.754105432,"remaining_time":41.47608049},
{"learn":[225269.9412],"iteration":83,"passed_time":3.797294592,"remaining_time":41.4085934},
{"learn":[224779.0067],"iteration":84,"passed_time":3.845563959,"remaining_time":41.39636497},
{"learn":[224357.469],"iteration":85,"passed_time":3.89359441,"remaining_time":41.38075919},
{"learn":[223833.6396],"iteration":86,"passed_time":3.946372155,"remaining_time":41.41422733},
{"learn":[223313.9907],"iteration":87,"passed_time":4.001684033,"remaining_time":41.47199816},
{"learn":[222935.4679],"iteration":88,"passed_time":4.06687004,"remaining_time":41.62829895},
{"learn":[222492.6388],"iteration":89,"passed_time":4.136990435,"remaining_time":41.82956996},
{"learn":[222062.4038],"iteration":90,"passed_time":4.206649962,"remaining_time":42.0202727},
{"learn":[221610.1655],"iteration":91,"passed_time":4.274682601,"remaining_time":42.18925871},
{"learn":[221181.3269],"iteration":92,"passed_time":4.401075434,"remaining_time":42.92231633},
{"learn":[220862.5952],"iteration":93,"passed_time":4.462977534,"remaining_time":43.01550687},
{"learn":[220593.1229],"iteration":94,"passed_time":4.499032523,"remaining_time":42.85920456},
{"learn":[220259.8548],"iteration":95,"passed_time":4.541952096,"remaining_time":42.7700489},
{"learn":[219969.6365],"iteration":96,"passed_time":4.590105975,"remaining_time":42.73057418},
{"learn":[219675.6402],"iteration":97,"passed_time":4.619995552,"remaining_time":42.5228162},
{"learn":[219323.0479],"iteration":98,"passed_time":4.662136196,"remaining_time":42.43014861},
{"learn":[219041.9422],"iteration":99,"passed_time":4.70698708,"remaining_time":42.36288372},
{"learn":[218725.5255],"iteration":100,"passed_time":4.748336617,"remaining_time":42.26489721},
{"learn":[218433.0702],"iteration":101,"passed_time":4.792493784,"remaining_time":42.19273939},
{"learn":[218135.1339],"iteration":102,"passed_time":4.828980108,"remaining_time":42.05432192},
{"learn":[217874.9891],"iteration":103,"passed_time":4.874687142,"remaining_time":41.99730461},
{"learn":[217602.6876],"iteration":104,"passed_time":4.92226658,"remaining_time":41.95646275},
{"learn":[217405.1506],"iteration":105,"passed_time":4.96580998,"remaining_time":41.88145398},
{"learn":[217188.7473],"iteration":106,"passed_time":5.009995347,"remaining_time":41.81239108},
{"learn":[217009.4789],"iteration":107,"passed_time":5.059279688,"remaining_time":41.78590261},
{"learn":[216764.2199],"iteration":108,"passed_time":5.106090824,"remaining_time":41.73877912},
{"learn":[216529.2678],"iteration":109,"passed_time":5.15237914,"remaining_time":41.68743122},
{"learn":[216333.7104],"iteration":110,"passed_time":5.197963253,"remaining_time":41.63053452},
{"learn":[216141.1363],"iteration":111,"passed_time":5.240139508,"remaining_time":41.54682039},
{"learn":[216011.8424],"iteration":112,"passed_time":5.287447584,"remaining_time":41.50412395},
{"learn":[215848.3526],"iteration":113,"passed_time":5.332099558,"remaining_time":41.44070359},
{"learn":[215726.5784],"iteration":114,"passed_time":5.355340326,"remaining_time":41.21283642},
{"learn":[215539.4946],"iteration":115,"passed_time":5.398023287,"remaining_time":41.13666022},
{"learn":[215373.2431],"iteration":116,"passed_time":5.44006624,"remaining_time":41.05622641},
{"learn":[215225.9042],"iteration":117,"passed_time":5.484889981,"remaining_time":40.9972285},
{"learn":[215101.703],"iteration":118,"passed_time":5.522893508,"remaining_time":40.88797631},
{"learn":[214817.3291],"iteration":119,"passed_time":5.571307186,"remaining_time":40.8562527},
{"learn":[214690.867],"iteration":120,"passed_time":5.614069776,"remaining_time":40.7832011},
{"learn":[214530.8835],"iteration":121,"passed_time":5.658181521,"remaining_time":40.72035553},
{"learn":[214336.3644],"iteration":122,"passed_time":5.689168224,"remaining_time":40.56423197},
{"learn":[214186.3234],"iteration":123,"passed_time":5.727884841,"remaining_time":40.46473484},
{"learn":[214043.8156],"iteration":124,"passed_time":5.770898809,"remaining_time":40.39629166},
{"learn":[213883.7346],"iteration":125,"passed_time":5.812030613,"remaining_time":40.31519647},
{"learn":[213773.8867],"iteration":126,"passed_time":5.854200629,"remaining_time":40.24186731},
{"learn":[213628.9604],"iteration":127,"passed_time":5.903296383,"remaining_time":40.21620661},
{"learn":[213533.6229],"iteration":128,"passed_time":5.930012064,"remaining_time":40.0390737},
{"learn":[213427.7766],"iteration":129,"passed_time":5.967197364,"remaining_time":39.93432082},
{"learn":[213342.7004],"iteration":130,"passed_time":6.012031953,"remaining_time":39.88134173},
{"learn":[213229.1817],"iteration":131,"passed_time":6.058161329,"remaining_time":39.83700025},
{"learn":[213147.9164],"iteration":132,"passed_time":6.092786625,"remaining_time":39.71763913},
{"learn":[213061.1207],"iteration":133,"passed_time":6.14399233,"remaining_time":39.7066967},
{"learn":[212935.0677],"iteration":134,"passed_time":6.193893555,"remaining_time":39.68679944},
{"learn":[212877.2617],"iteration":135,"passed_time":6.239425105,"remaining_time":39.63870067},
{"learn":[212801.0377],"iteration":136,"passed_time":6.28356417,"remaining_time":39.58186773},
{"learn":[212655.2986],"iteration":137,"passed_time":6.327054905,"remaining_time":39.52116904},
{"learn":[212552.4624],"iteration":138,"passed_time":6.37430902,"remaining_time":39.48402925},
{"learn":[212450.8801],"iteration":139,"passed_time":6.422091888,"remaining_time":39.44999303},
{"learn":[212332.883],"iteration":140,"passed_time":6.469430471,"remaining_time":39.41305514},
{"learn":[212237.5551],"iteration":141,"passed_time":6.516560308,"remaining_time":39.37470947},
{"learn":[212154.422],"iteration":142,"passed_time":6.564653766,"remaining_time":39.34201593},
{"learn":[212002.7197],"iteration":143,"passed_time":6.615783167,"remaining_time":39.32715549},
{"learn":[211918.2812],"iteration":144,"passed_time":6.687593783,"remaining_time":39.43374265},
{"learn":[211805.7533],"iteration":145,"passed_time":6.725296591,"remaining_time":39.33837869},
{"learn":[211745.6026],"iteration":146,"passed_time":6.792680858,"remaining_time":39.41603246},
{"learn":[211645.7848],"iteration":147,"passed_time":6.839262699,"remaining_time":39.37197175},
{"learn":[211587.8317],"iteration":148,"passed_time":6.883960271,"remaining_time":39.31711537},
{"learn":[211541.1588],"iteration":149,"passed_time":6.90944161,"remaining_time":39.15350246},
{"learn":[211462.4586],"iteration":150,"passed_time":6.952937121,"remaining_time":39.09300408},
{"learn":[211415.6802],"iteration":151,"passed_time":6.998942778,"remaining_time":39.04673339},
{"learn":[211350.9145],"iteration":152,"passed_time":7.045939417,"remaining_time":39.0059522},
{"learn":[211166.7148],"iteration":153,"passed_time":7.087229378,"remaining_time":38.93374061},
{"learn":[211092.6998],"iteration":154,"passed_time":7.122117961,"remaining_time":38.82703017},
{"learn":[211049.7885],"iteration":155,"passed_time":7.171083546,"remaining_time":38.79740072},
{"learn":[210917.2468],"iteration":156,"passed_time":7.22484739,"remaining_time":38.79328885},
{"learn":[210857.5706],"iteration":157,"passed_time":7.267389909,"remaining_time":38.72874875},
{"learn":[210842.2195],"iteration":158,"passed_time":7.288702702,"remaining_time":38.55219479},
{"learn":[210805.6585],"iteration":159,"passed_time":7.314146723,"remaining_time":38.39927029},
{"learn":[210755.2728],"iteration":160,"passed_time":7.360258004,"remaining_time":38.35563022},
{"learn":[210724.3426],"iteration":161,"passed_time":7.400570627,"remaining_time":38.28196411},
{"learn":[210677.3004],"iteration":162,"passed_time":7.441477884,"remaining_time":38.21176067},
{"learn":[210643.4776],"iteration":163,"passed_time":7.486368632,"remaining_time":38.16222059},
{"learn":[210532.2412],"iteration":164,"passed_time":7.522990126,"remaining_time":38.07088943},
{"learn":[210443.3753],"iteration":165,"passed_time":7.573205875,"remaining_time":38.04851626},
{"learn":[210411.509],"iteration":166,"passed_time":7.632130162,"remaining_time":38.06924805},
{"learn":[210377.9019],"iteration":167,"passed_time":7.68413911,"remaining_time":38.05478416},
{"learn":[210291.178],"iteration":168,"passed_time":7.737004187,"remaining_time":38.04408568},
{"learn":[210257.432],"iteration":169,"passed_time":7.780075019,"remaining_time":37.98507215},
{"learn":[210229.293],"iteration":170,"passed_time":7.827814407,"remaining_time":37.94887803},
{"learn":[210120.4951],"iteration":171,"passed_time":7.872981569,"remaining_time":37.90016709},
{"learn":[210071.0286],"iteration":172,"passed_time":7.920996004,"remaining_time":37.86510806},
{"learn":[210048.4622],"iteration":173,"passed_time":7.940744484,"remaining_time":37.69571807},
{"learn":[210023.9199],"iteration":174,"passed_time":7.996736805,"remaining_time":37.69890208},
{"learn":[209976.2314],"iteration":175,"passed_time":8.052021303,"remaining_time":37.69809974},
{"learn":[209919.3141],"iteration":176,"passed_time":8.099948199,"remaining_time":37.662471},
{"learn":[209899.2574],"iteration":177,"passed_time":8.133881541,"remaining_time":37.56208217},
{"learn":[209847.1237],"iteration":178,"passed_time":8.178757384,"remaining_time":37.51262465},
{"learn":[209788.3953],"iteration":179,"passed_time":8.222983685,"remaining_time":37.46025901},
{"learn":[209743.299],"iteration":180,"passed_time":8.270094725,"remaining_time":37.42103635},
{"learn":[209726.0435],"iteration":181,"passed_time":8.305300291,"remaining_time":37.32821779},
{"learn":[209663.8798],"iteration":182,"passed_time":8.356985663,"remaining_time":37.30960266},
{"learn":[209640.2071],"iteration":183,"passed_time":8.410402868,"remaining_time":37.29830837},
{"learn":[209609.402],"iteration":184,"passed_time":8.457905052,"remaining_time":37.26050063},
{"learn":[209593.6774],"iteration":185,"passed_time":8.487298618,"remaining_time":37.14333911},
{"learn":[209480.0969],"iteration":186,"passed_time":8.540590151,"remaining_time":37.13101493},
{"learn":[209464.6906],"iteration":187,"passed_time":8.569193834,"remaining_time":37.01162443},
{"learn":[209397.2345],"iteration":188,"passed_time":8.618100631,"remaining_time":36.9803154},
{"learn":[209285.0636],"iteration":189,"passed_time":8.662597018,"remaining_time":36.93001887},
{"learn":[209270.6638],"iteration":190,"passed_time":8.696313476,"remaining_time":36.83412357},
{"learn":[209257.6309],"iteration":191,"passed_time":8.726018809,"remaining_time":36.72199582},
{"learn":[209226.2949],"iteration":192,"passed_time":8.7615294,"remaining_time":36.63499599},
{"learn":[209114.0627],"iteration":193,"passed_time":8.803426051,"remaining_time":36.57505875},
{"learn":[209076.138],"iteration":194,"passed_time":8.847412577,"remaining_time":36.52393397},
{"learn":[209016.6551],"iteration":195,"passed_time":8.890809422,"remaining_time":36.47046314},
{"learn":[209002.7794],"iteration":196,"passed_time":8.934442513,"remaining_time":36.41805755},
{"learn":[208976.8617],"iteration":197,"passed_time":8.978093499,"remaining_time":36.36581306},
{"learn":[208925.9654],"iteration":198,"passed_time":9.022924165,"remaining_time":36.3184033},
{"learn":[208916.8413],"iteration":199,"passed_time":9.051977018,"remaining_time":36.20790807},
{"learn":[208906.7052],"iteration":200,"passed_time":9.081486842,"remaining_time":36.10003974},
{"learn":[208858.8248],"iteration":201,"passed_time":9.122494019,"remaining_time":36.03836746},
{"learn":[208811.9623],"iteration":202,"passed_time":9.163150153,"remaining_time":35.97552055},
{"learn":[208783.0811],"iteration":203,"passed_time":9.197490888,"remaining_time":35.88824876},
{"learn":[208729.0637],"iteration":204,"passed_time":9.240871771,"remaining_time":35.8365515},
{"learn":[208700.8903],"iteration":205,"passed_time":9.281271229,"remaining_time":35.77344347},
{"learn":[208689.2007],"iteration":206,"passed_time":9.31550312,"remaining_time":35.68692741},
{"learn":[208683.0497],"iteration":207,"passed_time":9.356092938,"remaining_time":35.62512311},
{"learn":[208674.1582],"iteration":208,"passed_time":9.374759819,"remaining_time":35.48055032},
{"learn":[208656.9601],"iteration":209,"passed_time":9.399704268,"remaining_time":35.36079225},
{"learn":[208648.8763],"iteration":210,"passed_time":9.455207096,"remaining_time":35.35620094},
{"learn":[208637.7192],"iteration":211,"passed_time":9.500412344,"remaining_time":35.31285343},
{"learn":[208630.3751],"iteration":212,"passed_time":9.527085078,"remaining_time":35.20101388},
{"learn":[208600.1326],"iteration":213,"passed_time":9.566726325,"remaining_time":35.1376023},
{"learn":[208593.9203],"iteration":214,"passed_time":9.58797321,"remaining_time":35.00725102},
{"learn":[208587.0073],"iteration":215,"passed_time":9.631110988,"remaining_time":34.95736581},
{"learn":[208541.2106],"iteration":216,"passed_time":9.675238377,"remaining_time":34.91111359},
{"learn":[208535.1812],"iteration":217,"passed_time":9.70818953,"remaining_time":34.82478996},
{"learn":[208447.2572],"iteration":218,"passed_time":9.748289704,"remaining_time":34.76444867},
{"learn":[208441.0087],"iteration":219,"passed_time":9.783969538,"remaining_time":34.68861927},
{"learn":[208434.4083],"iteration":220,"passed_time":9.818644837,"remaining_time":34.60961235},
{"learn":[208426.2748],"iteration":221,"passed_time":9.851712042,"remaining_time":34.52536923},
{"learn":[208420.8131],"iteration":222,"passed_time":9.887139499,"remaining_time":34.44980893},
{"learn":[208416.3739],"iteration":223,"passed_time":9.91302763,"remaining_time":34.34156},
{"learn":[208333.924],"iteration":224,"passed_time":9.956087939,"remaining_time":34.29319179},
{"learn":[208312.0041],"iteration":225,"passed_time":10.00351411,"remaining_time":34.25982267},
{"learn":[208239.9736],"iteration":226,"passed_time":10.04852805,"remaining_time":34.21811534},
{"learn":[208181.5349],"iteration":227,"passed_time":10.09230964,"remaining_time":34.17220632},
{"learn":[208178.145],"iteration":228,"passed_time":10.12085146,"remaining_time":34.07500644},
{"learn":[208161.2301],"iteration":229,"passed_time":10.15020501,"remaining_time":33.98112113},
{"learn":[208149.1971],"iteration":230,"passed_time":10.19404423,"remaining_time":33.93601737},
{"learn":[208082.238],"iteration":231,"passed_time":10.23792079,"remaining_time":33.89104813},
{"learn":[208061.1162],"iteration":232,"passed_time":10.26643815,"remaining_time":33.79552816},
{"learn":[208052.8395],"iteration":233,"passed_time":10.31783513,"remaining_time":33.7754774},
{"learn":[208047.0449],"iteration":234,"passed_time":10.34193491,"remaining_time":33.66629876},
{"learn":[208025.8655],"iteration":235,"passed_time":10.3862137,"remaining_time":33.6231664},
{"learn":[208020.3328],"iteration":236,"passed_time":10.42491702,"remaining_time":33.56207462},
{"learn":[207964.5042],"iteration":237,"passed_time":10.47060957,"remaining_time":33.52354829},
{"learn":[207909.5239],"iteration":238,"passed_time":10.54303867,"remaining_time":33.57009385},
{"learn":[207885.2903],"iteration":239,"passed_time":10.58910706,"remaining_time":33.53217236},
{"learn":[207882.6774],"iteration":240,"passed_time":10.61879761,"remaining_time":33.44260326},
{"learn":[207879.6591],"iteration":241,"passed_time":10.65515362,"remaining_time":33.3744068},
{"learn":[207820.2885],"iteration":242,"passed_time":10.71340516,"remaining_time":33.37468191},
{"learn":[207793.5083],"iteration":243,"passed_time":10.76434889,"remaining_time":33.35183508},
{"learn":[207771.8445],"iteration":244,"passed_time":10.81278613,"remaining_time":33.32103481},
{"learn":[207745.752],"iteration":245,"passed_time":10.85423127,"remaining_time":33.26866007},
{"learn":[207726.7637],"iteration":246,"passed_time":10.91255612,"remaining_time":33.26783302},
{"learn":[207724.8984],"iteration":247,"passed_time":10.93343364,"remaining_time":33.15299232},
{"learn":[207704.4735],"iteration":248,"passed_time":10.98765642,"remaining_time":33.13947779},
{"learn":[207652.8792],"iteration":249,"passed_time":11.03443911,"remaining_time":33.10331732},
{"learn":[207644.245],"iteration":250,"passed_time":11.08745914,"remaining_time":33.08568485},
{"learn":[207519.4396],"iteration":251,"passed_time":11.14141379,"remaining_time":33.0705457},
{"learn":[207515.3867],"iteration":252,"passed_time":11.17212357,"remaining_time":32.98646761},
{"learn":[207513.8606],"iteration":253,"passed_time":11.21813619,"remaining_time":32.94775433},
{"learn":[207512.3305],"iteration":254,"passed_time":11.25392302,"remaining_time":32.87910843},
{"learn":[207510.953],"iteration":255,"passed_time":11.27594658,"remaining_time":32.77071974},
{"learn":[207494.0293],"iteration":256,"passed_time":11.33061474,"remaining_time":32.75738037},
{"learn":[207490.2637],"iteration":257,"passed_time":11.36319233,"remaining_time":32.6801888},
{"learn":[207478.376],"iteration":258,"passed_time":11.41389394,"remaining_time":32.65519462},
{"learn":[207476.2548],"iteration":259,"passed_time":11.46622957,"remaining_time":32.63465338},
{"learn":[207475.1492],"iteration":260,"passed_time":11.49193098,"remaining_time":32.53845593},
{"learn":[207421.3111],"iteration":261,"passed_time":11.54195921,"remaining_time":32.51132021},
{"learn":[207341.0614],"iteration":262,"passed_time":11.5954711,"remaining_time":32.49377263},
{"learn":[207338.6218],"iteration":263,"passed_time":11.66438034,"remaining_time":32.51887851},
{"learn":[207335.1826],"iteration":264,"passed_time":11.70904746,"remaining_time":32.47603729},
{"learn":[207319.9779],"iteration":265,"passed_time":11.75531973,"remaining_time":32.43761158},
{"learn":[207252.0461],"iteration":266,"passed_time":11.78980822,"remaining_time":32.36677687},
{"learn":[207248.9658],"iteration":267,"passed_time":11.81478724,"remaining_time":32.27023978},
{"learn":[207231.7223],"iteration":268,"passed_time":11.88081451,"remaining_time":32.28578217},
{"learn":[207212.0592],"iteration":269,"passed_time":11.9344088,"remaining_time":32.26710526},
{"learn":[207197.8065],"iteration":270,"passed_time":11.99301767,"remaining_time":32.26166007},
{"learn":[207197.0232],"iteration":271,"passed_time":12.0237836,"remaining_time":32.18130316},
{"learn":[207185.2391],"iteration":272,"passed_time":12.07497949,"remaining_time":32.15571461},
{"learn":[207184.3882],"iteration":273,"passed_time":12.13170811,"remaining_time":32.14459887},
{"learn":[207183.6933],"iteration":274,"passed_time":12.17674141,"remaining_time":32.10231827},
{"learn":[207170.9847],"iteration":275,"passed_time":12.21430889,"remaining_time":32.04043348},
{"learn":[207114.0593],"iteration":276,"passed_time":12.26942042,"remaining_time":32.02451611},
{"learn":[207111.9675],"iteration":277,"passed_time":12.3298775,"remaining_time":32.02219985},
{"learn":[207110.985],"iteration":278,"passed_time":12.37663701,"remaining_time":31.98406911},
{"learn":[207066.3038],"iteration":279,"passed_time":12.45728263,"remaining_time":32.03301246},
{"learn":[207065.7642],"iteration":280,"passed_time":12.51188596,"remaining_time":32.01439861},
{"learn":[207065.3193],"iteration":281,"passed_time":12.53614722,"remaining_time":31.91827556},
{"learn":[207018.9222],"iteration":282,"passed_time":12.59316829,"remaining_time":31.90565958},
{"learn":[207016.2571],"iteration":283,"passed_time":12.66182224,"remaining_time":31.92205888},
{"learn":[207015.8503],"iteration":284,"passed_time":12.70002199,"remaining_time":31.86145869},
{"learn":[206998.2303],"iteration":285,"passed_time":12.75527941,"remaining_time":31.84359966},
{"learn":[206997.7603],"iteration":286,"passed_time":12.79546319,"remaining_time":31.78803225},
{"learn":[206974.0461],"iteration":287,"passed_time":12.85339779,"remaining_time":31.77645564},
{"learn":[206867.2059],"iteration":288,"passed_time":12.90424704,"remaining_time":31.7471268},
{"learn":[206833.3297],"iteration":289,"passed_time":12.95500836,"remaining_time":31.71743426},
{"learn":[206830.7447],"iteration":290,"passed_time":13.00497733,"remaining_time":31.68566641},
{"learn":[206820.0483],"iteration":291,"passed_time":13.06496166,"remaining_time":31.67805772},
{"learn":[206819.7777],"iteration":292,"passed_time":13.09336796,"remaining_time":31.59389471},
{"learn":[206817.4615],"iteration":293,"passed_time":13.13867624,"remaining_time":31.55069872},
{"learn":[206817.2136],"iteration":294,"passed_time":13.16041038,"remaining_time":31.45115023},
{"learn":[206803.9425],"iteration":295,"passed_time":13.20906797,"remaining_time":31.41616167},
{"learn":[206716.2809],"iteration":296,"passed_time":13.26107409,"remaining_time":31.38900702},
{"learn":[206706.5481],"iteration":297,"passed_time":13.31454014,"remaining_time":31.36512476},
{"learn":[206687.5737],"iteration":298,"passed_time":13.36619194,"remaining_time":31.33679114},
{"learn":[206674.9298],"iteration":299,"passed_time":13.41334719,"remaining_time":31.2978101},
{"learn":[206674.4115],"iteration":300,"passed_time":13.45216152,"remaining_time":31.23940498},
{"learn":[206674.2275],"iteration":301,"passed_time":13.48696678,"remaining_time":31.17186363},
{"learn":[206605.2201],"iteration":302,"passed_time":13.53584711,"remaining_time":31.13691563},
{"learn":[206605.0765],"iteration":303,"passed_time":13.55765531,"remaining_time":31.03989504},
{"learn":[206602.1996],"iteration":304,"passed_time":13.60175458,"remaining_time":30.99416208},
{"learn":[206602.0178],"iteration":305,"passed_time":13.63880497,"remaining_time":30.9324531},
{"learn":[206601.8307],"iteration":306,"passed_time":13.67174422,"remaining_time":30.86162458},
{"learn":[206497.6081],"iteration":307,"passed_time":13.72450311,"remaining_time":30.83557191},
{"learn":[206460.9985],"iteration":308,"passed_time":13.77608456,"remaining_time":30.80671337},
{"learn":[206459.7794],"iteration":309,"passed_time":13.81187613,"remaining_time":30.742563},
{"learn":[206438.2931],"iteration":310,"passed_time":13.85875563,"remaining_time":30.70315958},
{"learn":[206329.7256],"iteration":311,"passed_time":13.9079809,"remaining_time":30.66888096},
{"learn":[206323.6817],"iteration":312,"passed_time":13.95218677,"remaining_time":30.62348981},
{"learn":[206302.7243],"iteration":313,"passed_time":13.99667237,"remaining_time":30.57871734},
{"learn":[206300.7851],"iteration":314,"passed_time":14.03835006,"remaining_time":30.52784061},
{"learn":[206257.3409],"iteration":315,"passed_time":14.08297,"remaining_time":30.48339076},
{"learn":[206243.5168],"iteration":316,"passed_time":14.12001483,"remaining_time":30.4226187},
{"learn":[206241.8087],"iteration":317,"passed_time":14.14810681,"remaining_time":30.3427951},
{"learn":[206202.5199],"iteration":318,"passed_time":14.20014468,"remaining_time":30.31441544},
{"learn":[206110.5894],"iteration":319,"passed_time":14.24929996,"remaining_time":30.27976242},
{"learn":[206110.5249],"iteration":320,"passed_time":14.27373041,"remaining_time":30.19271947},
{"learn":[206079.3735],"iteration":321,"passed_time":14.31678961,"remaining_time":30.14528992},
{"learn":[206078.5432],"iteration":322,"passed_time":14.35088536,"remaining_time":30.07910027},
{"learn":[206065.4348],"iteration":323,"passed_time":14.39116934,"remaining_time":30.02601998},
{"learn":[206063.9165],"iteration":324,"passed_time":14.4108344,"remaining_time":29.93019452},
{"learn":[206044.6856],"iteration":325,"passed_time":14.46513012,"remaining_time":29.90643466},
{"learn":[206044.5719],"iteration":326,"passed_time":14.49163656,"remaining_time":29.82529481},
{"learn":[206043.0324],"iteration":327,"passed_time":14.53614724,"remaining_time":29.78137483},
{"learn":[206013.8461],"iteration":328,"passed_time":14.56593186,"remaining_time":29.70741727},
{"learn":[205910.8796],"iteration":329,"passed_time":14.61062409,"remaining_time":29.66399436},
{"learn":[205904.1366],"iteration":330,"passed_time":14.66406892,"remaining_time":29.63825411},
{"learn":[205902.6773],"iteration":331,"passed_time":14.69111388,"remaining_time":29.55922914},
{"learn":[205901.9891],"iteration":332,"passed_time":14.74347879,"remaining_time":29.5312323},
{"learn":[205865.0175],"iteration":333,"passed_time":14.79999778,"remaining_time":29.51137281},
{"learn":[205863.6431],"iteration":334,"passed_time":14.81865158,"remaining_time":29.41612925},
{"learn":[205855.8786],"iteration":335,"passed_time":14.87041183,"remaining_time":29.38676623},
{"learn":[205855.7882],"iteration":336,"passed_time":14.90673063,"remaining_time":29.32689141},
{"learn":[205855.2954],"iteration":337,"passed_time":14.94303264,"remaining_time":29.2671231},
{"learn":[205853.9107],"iteration":338,"passed_time":14.97463406,"remaining_time":29.19832777},
{"learn":[205852.6434],"iteration":339,"passed_time":15.00249502,"remaining_time":29.12249033},
{"learn":[205852.6189],"iteration":340,"passed_time":15.02766193,"remaining_time":29.0417279},
{"learn":[205827.4802],"iteration":341,"passed_time":15.07459582,"remaining_time":29.00316974},
{"learn":[205827.2885],"iteration":342,"passed_time":15.12510215,"remaining_time":28.97140557},
{"learn":[205827.2671],"iteration":343,"passed_time":15.14510708,"remaining_time":28.88136699},
{"learn":[205799.2147],"iteration":344,"passed_time":15.18636036,"remaining_time":28.83207547},
{"learn":[205790.2078],"iteration":345,"passed_time":15.23326597,"remaining_time":28.79351429},
{"learn":[205788.971],"iteration":346,"passed_time":15.28351169,"remaining_time":28.76119058},
{"learn":[205788.9578],"iteration":347,"passed_time":15.30881807,"remaining_time":28.68203845},
{"learn":[205788.893],"iteration":348,"passed_time":15.34690362,"remaining_time":28.62703226},
{"learn":[205772.7197],"iteration":349,"passed_time":15.39837654,"remaining_time":28.596985},
{"learn":[205762.6964],"iteration":350,"passed_time":15.44920794,"remaining_time":28.5656295},
{"learn":[205762.5609],"iteration":351,"passed_time":15.47811921,"remaining_time":28.49381036},
{"learn":[205714.1474],"iteration":352,"passed_time":15.53884994,"remaining_time":28.48055499},
{"learn":[205701.6499],"iteration":353,"passed_time":15.5894175,"remaining_time":28.44848505},
{"learn":[205698.892],"iteration":354,"passed_time":15.63825084,"remaining_time":28.41315997},
{"learn":[205620.2438],"iteration":355,"passed_time":15.69889043,"remaining_time":28.39911639},
{"learn":[205614.8488],"iteration":356,"passed_time":15.75035469,"remaining_time":28.36828589},
{"learn":[205614.8462],"iteration":357,"passed_time":15.77532473,"remaining_time":28.28982815},
{"learn":[205614.8438],"iteration":358,"passed_time":15.79633789,"remaining_time":28.2046033},
{"learn":[205585.153],"iteration":359,"passed_time":15.84757036,"remaining_time":28.17345841},
{"learn":[205575.3985],"iteration":360,"passed_time":15.90515446,"remaining_time":28.15344515},
{"learn":[205550.0382],"iteration":361,"passed_time":15.95613551,"remaining_time":28.12158689},
{"learn":[205549.0268],"iteration":362,"passed_time":15.9831295,"remaining_time":28.04753028},
{"learn":[205528.9975],"iteration":363,"passed_time":16.03031365,"remaining_time":28.00900956},
{"learn":[205512.7004],"iteration":364,"passed_time":16.07256002,"remaining_time":27.96185099},
{"learn":[205495.2106],"iteration":365,"passed_time":16.12459461,"remaining_time":27.93167481},
{"learn":[205489.6448],"iteration":366,"passed_time":16.16761705,"remaining_time":27.8858354},
{"learn":[205480.1942],"iteration":367,"passed_time":16.2105787,"remaining_time":27.8399069},
{"learn":[205372.5892],"iteration":368,"passed_time":16.25396426,"remaining_time":27.79471937},
{"learn":[205334.4545],"iteration":369,"passed_time":16.29649246,"remaining_time":27.74808176},
{"learn":[205333.5133],"iteration":370,"passed_time":16.32092935,"remaining_time":27.67079396},
{"learn":[205322.2662],"iteration":371,"passed_time":16.36259872,"remaining_time":27.62288171},
{"learn":[205322.2648],"iteration":372,"passed_time":16.38478165,"remaining_time":27.54224691},
{"learn":[205221.2017],"iteration":373,"passed_time":16.42837572,"remaining_time":27.49776256},
{"learn":[205215.6112],"iteration":374,"passed_time":16.45517167,"remaining_time":27.42528612},
{"learn":[205215.6073],"iteration":375,"passed_time":16.48041357,"remaining_time":27.35047359},
{"learn":[205215.6035],"iteration":376,"passed_time":16.5042237,"remaining_time":27.27355799},
{"learn":[205215.5433],"iteration":377,"passed_time":16.52888973,"remaining_time":27.19833178},
{"learn":[205213.0152],"iteration":378,"passed_time":16.55654925,"remaining_time":27.12827727},
{"learn":[205212.9693],"iteration":379,"passed_time":16.58050782,"remaining_time":27.05240749},
{"learn":[205166.2203],"iteration":380,"passed_time":16.62253462,"remaining_time":27.00616517},
{"learn":[205155.4241],"iteration":381,"passed_time":16.66192637,"remaining_time":26.95568193},
{"learn":[205153.0243],"iteration":382,"passed_time":16.70176115,"remaining_time":26.90597032},
{"learn":[205152.2393],"iteration":383,"passed_time":16.72178377,"remaining_time":26.82452813},
{"learn":[205151.4479],"iteration":384,"passed_time":16.75155075,"remaining_time":26.75897068},
{"learn":[205151.4425],"iteration":385,"passed_time":16.77141358,"remaining_time":26.6778444},
{"learn":[205042.9789],"iteration":386,"passed_time":16.81487657,"remaining_time":26.63441689},
{"learn":[205026.9149],"iteration":387,"passed_time":16.84519864,"remaining_time":26.57026178},
{"learn":[205026.1126],"iteration":388,"passed_time":16.86926953,"remaining_time":26.49646192},
{"learn":[205025.3317],"iteration":389,"passed_time":16.89767035,"remaining_time":26.42968953},
{"learn":[205025.3275],"iteration":390,"passed_time":16.91727737,"remaining_time":26.34941667},
{"learn":[205025.28],"iteration":391,"passed_time":16.94672259,"remaining_time":26.28471259},
{"learn":[205024.5209],"iteration":392,"passed_time":16.9745382,"remaining_time":26.21767096},
{"learn":[205016.9251],"iteration":393,"passed_time":17.00293549,"remaining_time":26.15172311},
{"learn":[204947.7687],"iteration":394,"passed_time":17.04590109,"remaining_time":26.10827889},
{"learn":[204938.3806],"iteration":395,"passed_time":17.08036869,"remaining_time":26.05187547},
{"learn":[204938.3555],"iteration":396,"passed_time":17.11041505,"remaining_time":25.98886719},
{"learn":[204937.6529],"iteration":397,"passed_time":17.12852759,"remaining_time":25.9079739},
{"learn":[204929.0583],"iteration":398,"passed_time":17.16288347,"remaining_time":25.85186207},
{"learn":[204929.0136],"iteration":399,"passed_time":17.19116249,"remaining_time":25.78674374},
{"learn":[204838.1848],"iteration":400,"passed_time":17.23820559,"remaining_time":25.74983827},
{"learn":[204789.4856],"iteration":401,"passed_time":17.28241292,"remaining_time":25.708664},
{"learn":[204789.4326],"iteration":402,"passed_time":17.3106572,"remaining_time":25.64382717},
{"learn":[204788.182],"iteration":403,"passed_time":17.35119211,"remaining_time":25.59730321},
{"learn":[204752.6678],"iteration":404,"passed_time":17.39920369,"remaining_time":25.56179308},
{"learn":[204752.623],"iteration":405,"passed_time":17.42895088,"remaining_time":25.49949957},
{"learn":[204745.5475],"iteration":406,"passed_time":17.47140575,"remaining_time":25.4558811},
{"learn":[204705.9365],"iteration":407,"passed_time":17.51622595,"remaining_time":25.4157004},
{"learn":[204627.0465],"iteration":408,"passed_time":17.56004728,"remaining_time":25.37405365},
{"learn":[204626.2733],"iteration":409,"passed_time":17.6058382,"remaining_time":25.33523058},
{"learn":[204625.5681],"iteration":410,"passed_time":17.63658194,"remaining_time":25.27480964},
{"learn":[204625.1718],"iteration":411,"passed_time":17.68331466,"remaining_time":25.237352},
{"learn":[204625.1299],"iteration":412,"passed_time":17.71451054,"remaining_time":25.17776679},
{"learn":[204625.125],"iteration":413,"passed_time":17.7387111,"remaining_time":25.10841717},
{"learn":[204625.0841],"iteration":414,"passed_time":17.77007833,"remaining_time":25.04938752},
{"learn":[204625.0795],"iteration":415,"passed_time":17.79620661,"remaining_time":24.9831362},
{"learn":[204585.361],"iteration":416,"passed_time":17.84190923,"remaining_time":24.94444384},
{"learn":[204584.61],"iteration":417,"passed_time":17.88803006,"remaining_time":24.90630022},
{"learn":[204584.0329],"iteration":418,"passed_time":17.90979138,"remaining_time":24.83434079},
{"learn":[204583.473],"iteration":419,"passed_time":17.9284395,"remaining_time":24.75832121},
{"learn":[204582.894],"iteration":420,"passed_time":17.95386602,"remaining_time":24.69189649},
{"learn":[204576.6003],"iteration":421,"passed_time":17.98412906,"remaining_time":24.63229051},
{"learn":[204576.5901],"iteration":422,"passed_time":18.0070419,"remaining_time":24.56279711},
{"learn":[204575.7255],"iteration":423,"passed_time":18.04418163,"remaining_time":24.51285052},
{"learn":[204575.6721],"iteration":424,"passed_time":18.08110263,"remaining_time":24.46266826},
{"learn":[204569.2143],"iteration":425,"passed_time":18.12566077,"remaining_time":24.42283869},
{"learn":[204556.5024],"iteration":426,"passed_time":18.17253248,"remaining_time":24.38609159},
{"learn":[204556.4595],"iteration":427,"passed_time":18.20666688,"remaining_time":24.33227443},
{"learn":[204556.4524],"iteration":428,"passed_time":18.22964643,"remaining_time":24.26370189},
{"learn":[204556.4442],"iteration":429,"passed_time":18.25452027,"remaining_time":24.19785245},
{"learn":[204556.4363],"iteration":430,"passed_time":18.2808714,"remaining_time":24.13414344},
{"learn":[204556.4301],"iteration":431,"passed_time":18.30475524,"remaining_time":24.06736337},
{"learn":[204556.3893],"iteration":432,"passed_time":18.3368376,"remaining_time":24.01151714},
{"learn":[204549.9418],"iteration":433,"passed_time":18.38072631,"remaining_time":23.97117763},
{"learn":[204548.5266],"iteration":434,"passed_time":18.40942676,"remaining_time":23.91109453},
{"learn":[204547.9226],"iteration":435,"passed_time":18.45262884,"remaining_time":23.86991438},
{"learn":[204547.9158],"iteration":436,"passed_time":18.47525007,"remaining_time":23.80221004},
{"learn":[204534.5558],"iteration":437,"passed_time":18.52386976,"remaining_time":23.76807033},
{"learn":[204525.6926],"iteration":438,"passed_time":18.57208892,"remaining_time":23.73335281},
{"learn":[204525.6545],"iteration":439,"passed_time":18.60302796,"remaining_time":23.67658104},
{"learn":[204518.0032],"iteration":440,"passed_time":18.65480479,"remaining_time":23.64633986},
{"learn":[204484.162],"iteration":441,"passed_time":18.69711488,"remaining_time":23.60405001},
{"learn":[204480.1518],"iteration":442,"passed_time":18.74827782,"remaining_time":23.57289108},
{"learn":[204426.1964],"iteration":443,"passed_time":18.79413868,"remaining_time":23.53500249},
{"learn":[204426.1426],"iteration":444,"passed_time":18.82868285,"remaining_time":23.482964},
{"learn":[204426.1019],"iteration":445,"passed_time":18.86106699,"remaining_time":23.42832088},
{"learn":[204301.4732],"iteration":446,"passed_time":18.90565849,"remaining_time":23.38887952},
{"learn":[204301.4627],"iteration":447,"passed_time":18.92957893,"remaining_time":23.32394547},
{"learn":[204301.4226],"iteration":448,"passed_time":18.96278408,"remaining_time":23.27058804},
{"learn":[204301.3846],"iteration":449,"passed_time":18.98991728,"remaining_time":23.20989889},
{"learn":[204301.3742],"iteration":450,"passed_time":19.01838336,"remaining_time":23.15098107},
{"learn":[204294.0512],"iteration":451,"passed_time":19.06625542,"remaining_time":23.1157256},
{"learn":[204293.6218],"iteration":452,"passed_time":19.09594438,"remaining_time":23.05845822},
{"learn":[204293.5856],"iteration":453,"passed_time":19.12440803,"remaining_time":22.99983873},
{"learn":[204293.2758],"iteration":454,"passed_time":19.16817733,"remaining_time":22.95968493},
{"learn":[204287.6594],"iteration":455,"passed_time":19.20351692,"remaining_time":22.90945878},
{"learn":[204284.3197],"iteration":456,"passed_time":19.24036731,"remaining_time":22.86109289},
{"learn":[204280.6379],"iteration":457,"passed_time":19.30864749,"remaining_time":22.84997148},
{"learn":[204279.3844],"iteration":458,"passed_time":19.34528541,"remaining_time":22.80130589},
{"learn":[204277.2591],"iteration":459,"passed_time":19.37888433,"remaining_time":22.74912508},
{"learn":[204274.0279],"iteration":460,"passed_time":19.4245374,"remaining_time":22.71111856},
{"learn":[204263.6249],"iteration":461,"passed_time":19.47074427,"remaining_time":22.67372385},
{"learn":[204086.7212],"iteration":462,"passed_time":19.51803909,"remaining_time":22.6375529},
{"learn":[204086.6835],"iteration":463,"passed_time":19.54604514,"remaining_time":22.57905214},
{"learn":[204086.6418],"iteration":464,"passed_time":19.58885697,"remaining_time":22.53771716},
{"learn":[204086.606],"iteration":465,"passed_time":19.61989849,"remaining_time":22.48288797},
{"learn":[204080.3501],"iteration":466,"passed_time":19.67431408,"remaining_time":22.45483812},
{"learn":[204080.289],"iteration":467,"passed_time":19.72102962,"remaining_time":22.41792256},
{"learn":[204080.2811],"iteration":468,"passed_time":19.74653892,"remaining_time":22.35695558},
{"learn":[204067.4327],"iteration":469,"passed_time":19.80364172,"remaining_time":22.3317662},
{"learn":[204064.5849],"iteration":470,"passed_time":19.82736601,"remaining_time":22.26895248},
{"learn":[204064.5519],"iteration":471,"passed_time":19.86211474,"remaining_time":22.21863683},
{"learn":[204064.1897],"iteration":472,"passed_time":19.88554554,"remaining_time":22.15577696},
{"learn":[204064.1582],"iteration":473,"passed_time":19.912691,"remaining_time":22.09720562},
{"learn":[204064.1263],"iteration":474,"passed_time":19.94677343,"remaining_time":22.04643379},
{"learn":[204058.1561],"iteration":475,"passed_time":19.99619037,"remaining_time":22.01261293},
{"learn":[204058.1273],"iteration":476,"passed_time":20.03097817,"remaining_time":21.96268676},
{"learn":[204058.1003],"iteration":477,"passed_time":20.05830176,"remaining_time":21.90467263},
{"learn":[203993.0243],"iteration":478,"passed_time":20.1117778,"remaining_time":21.87523222},
{"learn":[203958.9517],"iteration":479,"passed_time":20.16733243,"remaining_time":21.84794346},
{"learn":[203946.7395],"iteration":480,"passed_time":20.21337163,"remaining_time":21.81027001},
{"learn":[203946.7156],"iteration":481,"passed_time":20.23580226,"remaining_time":21.74718998},
{"learn":[203939.9428],"iteration":482,"passed_time":20.2654282,"remaining_time":21.69198008},
{"learn":[203919.9992],"iteration":483,"passed_time":20.30958903,"remaining_time":21.65237177},
{"learn":[203823.0023],"iteration":484,"passed_time":20.35738462,"remaining_time":21.61660429},
{"learn":[203817.6287],"iteration":485,"passed_time":20.39737256,"remaining_time":21.57252983},
{"learn":[203817.2831],"iteration":486,"passed_time":20.42357269,"remaining_time":21.51394824},
{"learn":[203817.2588],"iteration":487,"passed_time":20.45064794,"remaining_time":21.45641751},
{"learn":[203812.1451],"iteration":488,"passed_time":20.49040938,"remaining_time":21.41226829},
{"learn":[203804.9839],"iteration":489,"passed_time":20.5366744,"remaining_time":21.37490601},
{"learn":[203804.6464],"iteration":490,"passed_time":20.5665598,"remaining_time":21.32052737},
{"learn":[203804.6455],"iteration":491,"passed_time":20.58936047,"remaining_time":21.25893317},
{"learn":[203799.7067],"iteration":492,"passed_time":20.63481337,"remaining_time":21.22079185},
{"learn":[203690.6074],"iteration":493,"passed_time":20.67784009,"remaining_time":21.1801358},
{"learn":[203686.7617],"iteration":494,"passed_time":20.72813617,"remaining_time":21.14688639},
{"learn":[203618.6351],"iteration":495,"passed_time":20.78449297,"remaining_time":21.11972673},
{"learn":[203618.3051],"iteration":496,"passed_time":20.81265255,"remaining_time":21.06391194},
{"learn":[203614.0514],"iteration":497,"passed_time":20.84772397,"remaining_time":21.01517556},
{"learn":[203571.2202],"iteration":498,"passed_time":20.90442061,"remaining_time":20.98820586},
{"learn":[203517.8878],"iteration":499,"passed_time":20.95528256,"remaining_time":20.95528256},
{"learn":[203517.7094],"iteration":500,"passed_time":20.99255135,"remaining_time":20.90874875},
{"learn":[203517.4569],"iteration":501,"passed_time":21.02088747,"remaining_time":20.85339036},
{"learn":[203512.2008],"iteration":502,"passed_time":21.06486625,"remaining_time":20.81359548},
{"learn":[203512.1771],"iteration":503,"passed_time":21.09372418,"remaining_time":20.75890316},
{"learn":[203512.155],"iteration":504,"passed_time":21.11871412,"remaining_time":20.70052176},
{"learn":[203511.8359],"iteration":505,"passed_time":21.14450232,"remaining_time":20.64305167},
{"learn":[203509.6864],"iteration":506,"passed_time":21.17056937,"remaining_time":20.58597772},
{"learn":[203509.3824],"iteration":507,"passed_time":21.19525744,"remaining_time":20.52769028},
{"learn":[203509.3767],"iteration":508,"passed_time":21.21452738,"remaining_time":20.46430834},
{"learn":[203504.1402],"iteration":509,"passed_time":21.24881404,"remaining_time":20.41552722},
{"learn":[203504.1176],"iteration":510,"passed_time":21.27742847,"remaining_time":20.36137479},
{"learn":[203504.0955],"iteration":511,"passed_time":21.30242248,"remaining_time":20.30387143},
{"learn":[203503.1584],"iteration":512,"passed_time":21.34866239,"remaining_time":20.2666639},
{"learn":[203496.6235],"iteration":513,"passed_time":21.39764452,"remaining_time":20.23201408},
{"learn":[203486.005],"iteration":514,"passed_time":21.44626504,"remaining_time":20.19696805},
{"learn":[203485.9816],"iteration":515,"passed_time":21.47097715,"remaining_time":20.13944368},
{"learn":[203459.0114],"iteration":516,"passed_time":21.51443179,"remaining_time":20.0995562},
{"learn":[203458.7407],"iteration":517,"passed_time":21.53859722,"remaining_time":20.04170629},
{"learn":[203420.7944],"iteration":518,"passed_time":21.57166327,"remaining_time":19.99223513},
{"learn":[203397.5815],"iteration":519,"passed_time":21.61384845,"remaining_time":19.95124472},
{"learn":[203382.1458],"iteration":520,"passed_time":21.65803536,"remaining_time":19.91209009},
{"learn":[203283.0673],"iteration":521,"passed_time":21.70138095,"remaining_time":19.87214577},
{"learn":[203275.6654],"iteration":522,"passed_time":21.74467357,"remaining_time":19.83214014},
{"learn":[203275.6128],"iteration":523,"passed_time":21.77441576,"remaining_time":19.77981279},
{"learn":[203275.3561],"iteration":524,"passed_time":21.80215731,"remaining_time":19.72576138},
{"learn":[203275.1843],"iteration":525,"passed_time":21.83337424,"remaining_time":19.67494181},
{"learn":[203275.1342],"iteration":526,"passed_time":21.86324779,"remaining_time":19.6229909},
{"learn":[203274.8851],"iteration":527,"passed_time":21.89283835,"remaining_time":19.57087064},
{"learn":[203274.8369],"iteration":528,"passed_time":21.91645392,"remaining_time":19.51351569},
{"learn":[203274.7515],"iteration":529,"passed_time":21.94687997,"remaining_time":19.46232752},
{"learn":[203274.7191],"iteration":530,"passed_time":21.96611584,"remaining_time":19.40133396},
{"learn":[203274.674],"iteration":531,"passed_time":21.99039012,"remaining_time":19.34492965},
{"learn":[203270.5268],"iteration":532,"passed_time":22.04261238,"remaining_time":19.31313318},
{"learn":[203238.1739],"iteration":533,"passed_time":22.08597202,"remaining_time":19.27352615},
{"learn":[203203.4144],"iteration":534,"passed_time":22.12490698,"remaining_time":19.23005933},
{"learn":[203203.368],"iteration":535,"passed_time":22.14966058,"remaining_time":19.17433304},
{"learn":[203203.3223],"iteration":536,"passed_time":22.17803817,"remaining_time":19.12184669},
{"learn":[203200.1385],"iteration":537,"passed_time":22.21966331,"remaining_time":19.08082611},
{"learn":[203194.8892],"iteration":538,"passed_time":22.25855994,"remaining_time":19.03746963},
{"learn":[203174.0493],"iteration":539,"passed_time":22.29932618,"remaining_time":18.99572231},
{"learn":[203174.0214],"iteration":540,"passed_time":22.32139007,"remaining_time":18.93811099},
{"learn":[203169.2427],"iteration":541,"passed_time":22.36445545,"remaining_time":18.89837748},
{"learn":[203157.265],"iteration":542,"passed_time":22.39796503,"remaining_time":18.85058936},
{"learn":[203157.0754],"iteration":543,"passed_time":22.42355325,"remaining_time":18.79621375},
{"learn":[203081.4622],"iteration":544,"passed_time":22.46469503,"remaining_time":18.75492888},
{"learn":[203074.4018],"iteration":545,"passed_time":22.50482311,"remaining_time":18.71280164},
{"learn":[203069.4138],"iteration":546,"passed_time":22.54560423,"remaining_time":18.67122252},
{"learn":[203065.6578],"iteration":547,"passed_time":22.59586621,"remaining_time":18.63746629},
{"learn":[203065.6178],"iteration":548,"passed_time":22.62179417,"remaining_time":18.58365969},
{"learn":[203059.977],"iteration":549,"passed_time":22.66184783,"remaining_time":18.54151186},
{"learn":[203054.041],"iteration":550,"passed_time":22.70538422,"remaining_time":18.50220965},
{"learn":[203054.0071],"iteration":551,"passed_time":22.73099778,"remaining_time":18.44834602},
{"learn":[203047.2579],"iteration":552,"passed_time":22.77721647,"remaining_time":18.41124007},
{"learn":[203047.1009],"iteration":553,"passed_time":22.79863603,"remaining_time":18.35413659},
{"learn":[203043.5616],"iteration":554,"passed_time":22.84010059,"remaining_time":18.31323381},
{"learn":[203025.9373],"iteration":555,"passed_time":22.88239235,"remaining_time":18.27298958},
{"learn":[203025.2424],"iteration":556,"passed_time":22.9169479,"remaining_time":18.22658513},
{"learn":[202997.2201],"iteration":557,"passed_time":22.96210179,"remaining_time":18.18861826},
{"learn":[202997.1847],"iteration":558,"passed_time":22.98326301,"remaining_time":18.13169765},
{"learn":[202988.5852],"iteration":559,"passed_time":23.02869224,"remaining_time":18.09397248},
{"learn":[202986.4996],"iteration":560,"passed_time":23.07178398,"remaining_time":18.05439067},
{"learn":[202984.4286],"iteration":561,"passed_time":23.10727471,"remaining_time":18.00887246},
{"learn":[202984.3951],"iteration":562,"passed_time":23.13069507,"remaining_time":17.95402087},
{"learn":[202984.2402],"iteration":563,"passed_time":23.15550704,"remaining_time":17.90035651},
{"learn":[202981.5303],"iteration":564,"passed_time":23.19833164,"remaining_time":17.86066242},
{"learn":[202981.3943],"iteration":565,"passed_time":23.21824884,"remaining_time":17.80339222},
{"learn":[202980.8304],"iteration":566,"passed_time":23.26001115,"remaining_time":17.7629362},
{"learn":[202941.2664],"iteration":567,"passed_time":23.30897836,"remaining_time":17.72795537},
{"learn":[202941.2338],"iteration":568,"passed_time":23.32843402,"remaining_time":17.67057129},
{"learn":[202915.2118],"iteration":569,"passed_time":23.37391432,"remaining_time":17.63295291},
{"learn":[202915.1585],"iteration":570,"passed_time":23.40544397,"remaining_time":17.58482568},
{"learn":[202910.8582],"iteration":571,"passed_time":23.44004713,"remaining_time":17.53905624},
{"learn":[202910.69],"iteration":572,"passed_time":23.47836176,"remaining_time":17.49609157},
{"learn":[202910.655],"iteration":573,"passed_time":23.50330596,"remaining_time":17.4432201},
{"learn":[202910.5244],"iteration":574,"passed_time":23.53042913,"remaining_time":17.39205632},
{"learn":[202910.4901],"iteration":575,"passed_time":23.55439137,"remaining_time":17.3386492},
{"learn":[202909.8552],"iteration":576,"passed_time":23.59662795,"remaining_time":17.29874112},
{"learn":[202906.7254],"iteration":577,"passed_time":23.63969816,"remaining_time":17.2594336},
{"learn":[202826.6657],"iteration":578,"passed_time":23.68396966,"remaining_time":17.22098657},
{"learn":[202826.6306],"iteration":579,"passed_time":23.70970371,"remaining_time":17.16909579},
{"learn":[202826.5969],"iteration":580,"passed_time":23.73508979,"remaining_time":17.1170441},
{"learn":[202790.1874],"iteration":581,"passed_time":23.78159874,"remaining_time":17.08025477},
{"learn":[202779.4738],"iteration":582,"passed_time":23.82743859,"remaining_time":17.04295351},
{"learn":[202752.7887],"iteration":583,"passed_time":23.87047286,"remaining_time":17.0036245},
{"learn":[202752.3684],"iteration":584,"passed_time":23.91466984,"remaining_time":16.96510767},
{"learn":[202695.7903],"iteration":585,"passed_time":23.96604614,"remaining_time":16.93164352},
{"learn":[202695.7666],"iteration":586,"passed_time":23.99061828,"remaining_time":16.87925954},
{"learn":[202695.7365],"iteration":587,"passed_time":24.02070059,"remaining_time":16.83083102},
{"learn":[202695.7074],"iteration":588,"passed_time":24.04838886,"remaining_time":16.78079426},
{"learn":[202695.6067],"iteration":589,"passed_time":24.07264517,"remaining_time":16.72844834},
{"learn":[202549.5358],"iteration":590,"passed_time":24.11981369,"remaining_time":16.69205381},
{"learn":[202524.0543],"iteration":591,"passed_time":24.16751387,"remaining_time":16.65598929},
{"learn":[202470.074],"iteration":592,"passed_time":24.22419525,"remaining_time":16.62604969},
{"learn":[202469.9711],"iteration":593,"passed_time":24.25675717,"remaining_time":16.57953436},
{"learn":[202469.9441],"iteration":594,"passed_time":24.28768757,"remaining_time":16.5319554},
{"learn":[202469.8437],"iteration":595,"passed_time":24.32269266,"remaining_time":16.48719435},
{"learn":[202469.7327],"iteration":596,"passed_time":24.35422555,"remaining_time":16.4401221},
{"learn":[202469.7057],"iteration":597,"passed_time":24.38074019,"remaining_time":16.38972835},
{"learn":[202453.0577],"iteration":598,"passed_time":24.42311549,"remaining_time":16.35003224},
{"learn":[202452.9601],"iteration":599,"passed_time":24.44922609,"remaining_time":16.29948406},
{"learn":[202452.9336],"iteration":600,"passed_time":24.47375717,"remaining_time":16.24796857},
{"learn":[202450.2977],"iteration":601,"passed_time":24.51528858,"remaining_time":16.20778215},
{"learn":[202430.3782],"iteration":602,"passed_time":24.56444894,"remaining_time":16.17261398},
{"learn":[202429.8393],"iteration":603,"passed_time":24.61117493,"remaining_time":16.13580343},
{"learn":[202429.7465],"iteration":604,"passed_time":24.6373343,"remaining_time":16.08553231},
{"learn":[202427.2479],"iteration":605,"passed_time":24.67159435,"remaining_time":16.04060755},
{"learn":[202396.9478],"iteration":606,"passed_time":24.71302173,"remaining_time":16.00035839},
{"learn":[202366.98],"iteration":607,"passed_time":24.75791515,"remaining_time":15.96234003},
{"learn":[202366.8882],"iteration":608,"passed_time":24.78410679,"remaining_time":15.91229188},
{"learn":[202361.5247],"iteration":609,"passed_time":24.8273994,"remaining_time":15.87325535},
{"learn":[202308.8535],"iteration":610,"passed_time":24.87347393,"remaining_time":15.83597604},
{"learn":[202306.9177],"iteration":611,"passed_time":24.91583251,"remaining_time":15.79631211},
{"learn":[202306.8839],"iteration":612,"passed_time":24.95381584,"remaining_time":15.75387721},
{"learn":[202306.5079],"iteration":613,"passed_time":25.01550438,"remaining_time":15.72635943},
{"learn":[202306.4807],"iteration":614,"passed_time":25.03793597,"remaining_time":15.67415504},
{"learn":[202283.3328],"iteration":615,"passed_time":25.07964421,"remaining_time":15.63406392},
{"learn":[202260.5834],"iteration":616,"passed_time":25.12394005,"remaining_time":15.5955738},
{"learn":[202260.5514],"iteration":617,"passed_time":25.147389,"remaining_time":15.54417896},
{"learn":[202258.4548],"iteration":618,"passed_time":25.18971661,"remaining_time":15.50449439},
{"learn":[202252.7166],"iteration":619,"passed_time":25.23741655,"remaining_time":15.46809401},
{"learn":[202239.652],"iteration":620,"passed_time":25.29486896,"remaining_time":15.43760924},
{"learn":[202238.7324],"iteration":621,"passed_time":25.34226167,"remaining_time":15.4009243},
{"learn":[202235.1353],"iteration":622,"passed_time":25.38572256,"remaining_time":15.36182569},
{"learn":[202213.4167],"iteration":623,"passed_time":25.42763941,"remaining_time":15.32178272},
{"learn":[202213.3273],"iteration":624,"passed_time":25.45276189,"remaining_time":15.27165713},
{"learn":[202207.9318],"iteration":625,"passed_time":25.50406859,"remaining_time":15.23725503},
{"learn":[202205.8722],"iteration":626,"passed_time":25.54998637,"remaining_time":15.19959317},
{"learn":[202205.7914],"iteration":627,"passed_time":25.579398,"remaining_time":15.15212748},
{"learn":[202199.7749],"iteration":628,"passed_time":25.62251852,"remaining_time":15.11280504},
{"learn":[202199.6502],"iteration":629,"passed_time":25.65744873,"remaining_time":15.06866036},
{"learn":[202199.5812],"iteration":630,"passed_time":25.69878905,"remaining_time":15.02829344},
{"learn":[202197.2773],"iteration":631,"passed_time":25.74369735,"remaining_time":14.99000099},
{"learn":[202197.2448],"iteration":632,"passed_time":25.77233619,"remaining_time":14.94225495},
{"learn":[202196.6746],"iteration":633,"passed_time":25.81291408,"remaining_time":14.90146144},
{"learn":[202151.3729],"iteration":634,"passed_time":25.85501341,"remaining_time":14.86154314},
{"learn":[202148.7952],"iteration":635,"passed_time":25.89577438,"remaining_time":14.820852},
{"learn":[202148.7577],"iteration":636,"passed_time":25.92092437,"remaining_time":14.77126459},
{"learn":[202097.5773],"iteration":637,"passed_time":25.96070692,"remaining_time":14.73005628},
{"learn":[202097.3585],"iteration":638,"passed_time":26.00466745,"remaining_time":14.69121275},
{"learn":[202087.4257],"iteration":639,"passed_time":26.04674809,"remaining_time":14.6512958},
{"learn":[202083.5105],"iteration":640,"passed_time":26.09073222,"remaining_time":14.61243817},
{"learn":[202078.4699],"iteration":641,"passed_time":26.13901993,"remaining_time":14.57596439},
{"learn":[202065.9284],"iteration":642,"passed_time":26.18300107,"remaining_time":14.53706281},
{"learn":[202065.9239],"iteration":643,"passed_time":26.20778212,"remaining_time":14.48753173},
{"learn":[202065.8437],"iteration":644,"passed_time":26.24404286,"remaining_time":14.44439568},
{"learn":[202013.335],"iteration":645,"passed_time":26.28867299,"remaining_time":14.40586724},
{"learn":[202013.2936],"iteration":646,"passed_time":26.31216464,"remaining_time":14.35578689},
{"learn":[202013.2538],"iteration":647,"passed_time":26.33669688,"remaining_time":14.30635386},
{"learn":[202013.1954],"iteration":648,"passed_time":26.36802002,"remaining_time":14.2606703},
{"learn":[202013.1568],"iteration":649,"passed_time":26.39193788,"remaining_time":14.21104347},
{"learn":[202011.6666],"iteration":650,"passed_time":26.43039568,"remaining_time":14.16929046},
{"learn":[202011.6128],"iteration":651,"passed_time":26.45806075,"remaining_time":14.12178703},
{"learn":[202009.7754],"iteration":652,"passed_time":26.50697167,"remaining_time":14.08563426},
{"learn":[202009.6785],"iteration":653,"passed_time":26.54281813,"remaining_time":14.04253069},
{"learn":[202009.4371],"iteration":654,"passed_time":26.57866269,"remaining_time":13.99944828},
{"learn":[202009.3942],"iteration":655,"passed_time":26.60352714,"remaining_time":13.95063008},
{"learn":[202008.0071],"iteration":656,"passed_time":26.64708377,"remaining_time":13.91164343},
{"learn":[202002.7405],"iteration":657,"passed_time":26.68833574,"remaining_time":13.87144502},
{"learn":[202002.6962],"iteration":658,"passed_time":26.71416646,"remaining_time":13.82326367},
{"learn":[202002.6574],"iteration":659,"passed_time":26.73422299,"remaining_time":13.77217548},
{"learn":[201998.2652],"iteration":660,"passed_time":26.78226994,"remaining_time":13.73553632},
{"learn":[201997.0718],"iteration":661,"passed_time":26.83015796,"remaining_time":13.69878156},
{"learn":[201996.6513],"iteration":662,"passed_time":26.86055487,"remaining_time":13.65310255},
{"learn":[201996.6075],"iteration":663,"passed_time":26.88596405,"remaining_time":13.60494567},
{"learn":[201962.7713],"iteration":664,"passed_time":26.93477932,"remaining_time":13.56864823},
{"learn":[201961.947],"iteration":665,"passed_time":27.00552971,"remaining_time":13.5433137},
{"learn":[201961.8931],"iteration":666,"passed_time":27.04382705,"remaining_time":13.50164079},
{"learn":[201961.7038],"iteration":667,"passed_time":27.08528073,"remaining_time":13.46154671},
{"learn":[201961.6517],"iteration":668,"passed_time":27.12052752,"remaining_time":13.41837759},
{"learn":[201960.9581],"iteration":669,"passed_time":27.17037211,"remaining_time":13.38242209},
{"learn":[201907.8926],"iteration":670,"passed_time":27.23096427,"remaining_time":13.35169485},
{"learn":[201906.8448],"iteration":671,"passed_time":27.27828325,"remaining_time":13.31440016},
{"learn":[201906.7904],"iteration":672,"passed_time":27.30725009,"remaining_time":13.26815866},
{"learn":[201906.7417],"iteration":673,"passed_time":27.33483435,"remaining_time":13.2212997},
{"learn":[201906.07],"iteration":674,"passed_time":27.36798242,"remaining_time":13.17717672},
{"learn":[201906.0184],"iteration":675,"passed_time":27.39785943,"remaining_time":13.13151842},
{"learn":[201882.2529],"iteration":676,"passed_time":27.45373598,"remaining_time":13.09831126},
{"learn":[201834.8028],"iteration":677,"passed_time":27.51433583,"remaining_time":13.06728044},
{"learn":[201834.7409],"iteration":678,"passed_time":27.54874786,"remaining_time":13.02378212},
{"learn":[201833.3633],"iteration":679,"passed_time":27.61616338,"remaining_time":12.99584159},
{"learn":[201833.326],"iteration":680,"passed_time":27.64914763,"remaining_time":12.95165653},
{"learn":[201831.885],"iteration":681,"passed_time":27.70530284,"remaining_time":12.91830836},
{"learn":[201830.8877],"iteration":682,"passed_time":27.73325941,"remaining_time":12.87180561},
{"learn":[201830.855],"iteration":683,"passed_time":27.77446402,"remaining_time":12.83147753},
{"learn":[201817.0315],"iteration":684,"passed_time":27.8405578,"remaining_time":12.80259227},
{"learn":[201814.6495],"iteration":685,"passed_time":27.91232817,"remaining_time":12.77619686},
{"learn":[201793.5389],"iteration":686,"passed_time":27.97551396,"remaining_time":12.74575818},
{"learn":[201793.4864],"iteration":687,"passed_time":28.01452523,"remaining_time":12.70426144},
{"learn":[201793.4361],"iteration":688,"passed_time":28.05086191,"remaining_time":12.66156466},
{"learn":[201793.4014],"iteration":689,"passed_time":28.08106885,"remaining_time":12.61613238},
{"learn":[201793.3646],"iteration":690,"passed_time":28.11084768,"remaining_time":12.57055272},
{"learn":[201793.3313],"iteration":691,"passed_time":28.15395975,"remaining_time":12.53095319},
{"learn":[201793.284],"iteration":692,"passed_time":28.19661391,"remaining_time":12.49114065},
{"learn":[201778.4782],"iteration":693,"passed_time":28.26628188,"remaining_time":12.46323092},
{"learn":[201754.4609],"iteration":694,"passed_time":28.32884468,"remaining_time":12.43208292},
{"learn":[201754.0572],"iteration":695,"passed_time":28.39397261,"remaining_time":12.40196505},
{"learn":[201751.6948],"iteration":696,"passed_time":28.47289215,"remaining_time":12.37774221},
{"learn":[201750.1859],"iteration":697,"passed_time":28.53233409,"remaining_time":12.34493538},
{"learn":[201750.1261],"iteration":698,"passed_time":28.57179899,"remaining_time":12.30344992},
{"learn":[201746.083],"iteration":699,"passed_time":28.62005171,"remaining_time":12.26573645},
{"learn":[201742.116],"iteration":700,"passed_time":28.68998432,"remaining_time":12.2372401},
{"learn":[201742.0881],"iteration":701,"passed_time":28.71800492,"remaining_time":12.190834},
{"learn":[201686.1351],"iteration":702,"passed_time":28.78102309,"remaining_time":12.1592658},
{"learn":[201684.7407],"iteration":703,"passed_time":28.83441926,"remaining_time":12.12356264},
{"learn":[201642.483],"iteration":704,"passed_time":28.89399729,"remaining_time":12.09039603},
{"learn":[201640.9492],"iteration":705,"passed_time":28.9519151,"remaining_time":12.05646323},
{"learn":[201640.6517],"iteration":706,"passed_time":29.01031738,"remaining_time":12.02266335},
{"learn":[201640.2177],"iteration":707,"passed_time":29.04451158,"remaining_time":11.97880986},
{"learn":[201640.1675],"iteration":708,"passed_time":29.07249254,"remaining_time":11.93243347},
{"learn":[201616.2019],"iteration":709,"passed_time":29.12946149,"remaining_time":11.89794906},
{"learn":[201608.6317],"iteration":710,"passed_time":29.18967028,"remaining_time":11.8647183},
{"learn":[201601.8217],"iteration":711,"passed_time":29.23601249,"remaining_time":11.82580281},
{"learn":[201601.6788],"iteration":712,"passed_time":29.28605752,"remaining_time":11.78835695},
{"learn":[201601.6381],"iteration":713,"passed_time":29.31914429,"remaining_time":11.74408301},
{"learn":[201601.5965],"iteration":714,"passed_time":29.35148228,"remaining_time":11.69954189},
{"learn":[201583.4293],"iteration":715,"passed_time":29.41171644,"remaining_time":11.66609982},
{"learn":[201546.1366],"iteration":716,"passed_time":29.47440511,"remaining_time":11.63355181},
{"learn":[201525.5039],"iteration":717,"passed_time":29.5378995,"remaining_time":11.60123629},
{"learn":[201491.5585],"iteration":718,"passed_time":29.60910091,"remaining_time":11.57184611},
{"learn":[201491.5194],"iteration":719,"passed_time":29.64606377,"remaining_time":11.5290248},
{"learn":[201491.4867],"iteration":720,"passed_time":29.67810939,"remaining_time":11.48431695},
{"learn":[201491.4509],"iteration":721,"passed_time":29.70572022,"remaining_time":11.43793659},
{"learn":[201491.4191],"iteration":722,"passed_time":29.73573704,"remaining_time":11.39252996},
{"learn":[201490.9341],"iteration":723,"passed_time":29.7914551,"remaining_time":11.35696355},
{"learn":[201490.9067],"iteration":724,"passed_time":29.82024208,"remaining_time":11.31112631},
{"learn":[201482.632],"iteration":725,"passed_time":29.87949901,"remaining_time":11.27683571},
{"learn":[201428.6509],"iteration":726,"passed_time":29.9373285,"remaining_time":11.24194041},
{"learn":[201416.5807],"iteration":727,"passed_time":30.00009007,"remaining_time":11.20882486},
{"learn":[201416.0929],"iteration":728,"passed_time":30.0382645,"remaining_time":11.1664879},
{"learn":[201365.9035],"iteration":729,"passed_time":30.0963493,"remaining_time":11.13152645},
{"learn":[201365.8497],"iteration":730,"passed_time":30.12595191,"remaining_time":11.08602061},
{"learn":[201351.4408],"iteration":731,"passed_time":30.1795866,"remaining_time":11.04935684},
{"learn":[201296.9579],"iteration":732,"passed_time":30.24707663,"remaining_time":11.01769367},
{"learn":[201296.8042],"iteration":733,"passed_time":30.31124863,"remaining_time":10.98473043},
{"learn":[201293.8475],"iteration":734,"passed_time":30.35913621,"remaining_time":10.94581102},
{"learn":[201249.0633],"iteration":735,"passed_time":30.42299691,"remaining_time":10.91259672},
{"learn":[201248.6886],"iteration":736,"passed_time":30.46942479,"remaining_time":10.87307832},
{"learn":[201183.7117],"iteration":737,"passed_time":30.52527272,"remaining_time":10.83688544},
{"learn":[201182.6369],"iteration":738,"passed_time":30.58381084,"remaining_time":10.80158948},
{"learn":[201181.6178],"iteration":739,"passed_time":30.62701795,"remaining_time":10.76084414},
{"learn":[201180.4389],"iteration":740,"passed_time":30.68776796,"remaining_time":10.72622389},
{"learn":[201174.3028],"iteration":741,"passed_time":30.74540402,"remaining_time":10.69045045},
{"learn":[201171.9874],"iteration":742,"passed_time":30.8051148,"remaining_time":10.6553358},
{"learn":[201143.8347],"iteration":743,"passed_time":30.86416751,"remaining_time":10.6199286},
{"learn":[201143.3473],"iteration":744,"passed_time":30.9208002,"remaining_time":10.5836296},
{"learn":[201142.5992],"iteration":745,"passed_time":30.96048635,"remaining_time":10.54150608},
{"learn":[201141.6173],"iteration":746,"passed_time":31.01929601,"remaining_time":10.50586599},
{"learn":[201141.5953],"iteration":747,"passed_time":31.05380971,"remaining_time":10.46197867},
{"learn":[201141.5506],"iteration":748,"passed_time":31.079857,"remaining_time":10.41527918},
{"learn":[201141.1822],"iteration":749,"passed_time":31.11574676,"remaining_time":10.37191559},
{"learn":[201141.1408],"iteration":750,"passed_time":31.14659264,"remaining_time":10.32689956},
{"learn":[201141.1179],"iteration":751,"passed_time":31.18054763,"remaining_time":10.28294656},
{"learn":[201138.1562],"iteration":752,"passed_time":31.23789934,"remaining_time":10.24669474},
{"learn":[201138.1375],"iteration":753,"passed_time":31.28244027,"remaining_time":10.2062073},
{"learn":[201138.0965],"iteration":754,"passed_time":31.30768948,"remaining_time":10.1594489},
{"learn":[201138.0782],"iteration":755,"passed_time":31.3458027,"remaining_time":10.11689928},
{"learn":[201138.0607],"iteration":756,"passed_time":31.38036407,"remaining_time":10.07322123},
{"learn":[201138.0289],"iteration":757,"passed_time":31.42015154,"remaining_time":10.03123572},
{"learn":[201138.0119],"iteration":758,"passed_time":31.45348513,"remaining_time":9.98720674},
{"learn":[201127.756],"iteration":759,"passed_time":31.51535384,"remaining_time":9.952217001},
{"learn":[201127.7216],"iteration":760,"passed_time":31.53966807,"remaining_time":9.905362247},
{"learn":[201092.6857],"iteration":761,"passed_time":31.6068937,"remaining_time":9.871969423},
{"learn":[201091.8359],"iteration":762,"passed_time":31.65197064,"remaining_time":9.831608181},
{"learn":[201090.7442],"iteration":763,"passed_time":31.71525224,"remaining_time":9.79685802},
{"learn":[201090.721],"iteration":764,"passed_time":31.76026559,"remaining_time":9.756421456},
{"learn":[201090.3711],"iteration":765,"passed_time":31.80526532,"remaining_time":9.715968779},
{"learn":[201090.3486],"iteration":766,"passed_time":31.83128577,"remaining_time":9.669738701},
{"learn":[201089.4317],"iteration":767,"passed_time":31.89122621,"remaining_time":9.633807918},
{"learn":[201088.4371],"iteration":768,"passed_time":31.93588397,"remaining_time":9.593223923},
{"learn":[201088.4048],"iteration":769,"passed_time":31.9643795,"remaining_time":9.54780167},
{"learn":[201087.5634],"iteration":770,"passed_time":32.00335868,"remaining_time":9.505537144},
{"learn":[201070.0436],"iteration":771,"passed_time":32.0656985,"remaining_time":9.470180386},
{"learn":[201070.0221],"iteration":772,"passed_time":32.09666036,"remaining_time":9.425539331},
{"learn":[201066.1624],"iteration":773,"passed_time":32.15893879,"remaining_time":9.390077735},
{"learn":[201066.1313],"iteration":774,"passed_time":32.18937891,"remaining_time":9.345303554},
{"learn":[201063.3666],"iteration":775,"passed_time":32.23947257,"remaining_time":9.306239505},
{"learn":[201062.596],"iteration":776,"passed_time":32.28102564,"remaining_time":9.264695903},
{"learn":[201030.7016],"iteration":777,"passed_time":32.33912083,"remaining_time":9.227872525},
{"learn":[201030.6831],"iteration":778,"passed_time":32.37133637,"remaining_time":9.183652551},
{"learn":[201023.5232],"iteration":779,"passed_time":32.43263016,"remaining_time":9.147664916},
{"learn":[201023.4921],"iteration":780,"passed_time":32.46530388,"remaining_time":9.103587131},
{"learn":[201023.4605],"iteration":781,"passed_time":32.50160601,"remaining_time":9.060550013},
{"learn":[200983.4026],"iteration":782,"passed_time":32.55279524,"remaining_time":9.021655897},
{"learn":[200982.779],"iteration":783,"passed_time":32.5880751,"remaining_time":8.978347222},
{"learn":[200980.8948],"iteration":784,"passed_time":32.64641826,"remaining_time":8.941375703},
{"learn":[200979.9121],"iteration":785,"passed_time":32.6870781,"remaining_time":8.89953526},
{"learn":[200979.8982],"iteration":786,"passed_time":32.71837639,"remaining_time":8.85516413},
{"learn":[200979.8654],"iteration":787,"passed_time":32.75203137,"remaining_time":8.811460217},
{"learn":[200979.3728],"iteration":788,"passed_time":32.80783286,"remaining_time":8.77370435},
{"learn":[200978.9263],"iteration":789,"passed_time":32.8625389,"remaining_time":8.735611605},
{"learn":[200962.6747],"iteration":790,"passed_time":32.9158577,"remaining_time":8.697110316},
{"learn":[200962.6608],"iteration":791,"passed_time":32.9452968,"remaining_time":8.652300171},
{"learn":[200962.4636],"iteration":792,"passed_time":32.97107303,"remaining_time":8.606572658},
{"learn":[200960.6573],"iteration":793,"passed_time":33.01739353,"remaining_time":8.566225524},
{"learn":[200960.6269],"iteration":794,"passed_time":33.05472107,"remaining_time":8.523544427},
{"learn":[200959.9124],"iteration":795,"passed_time":33.09122922,"remaining_time":8.480666786},
{"learn":[200959.739],"iteration":796,"passed_time":33.13047398,"remaining_time":8.438502155},
{"learn":[200956.3444],"iteration":797,"passed_time":33.18434292,"remaining_time":8.400046704},
{"learn":[200916.4772],"iteration":798,"passed_time":33.23230634,"remaining_time":8.360067051},
{"learn":[200907.7676],"iteration":799,"passed_time":33.28711641,"remaining_time":8.321779101},
{"learn":[200891.9959],"iteration":800,"passed_time":33.33772475,"remaining_time":8.282406024},
{"learn":[200884.445],"iteration":801,"passed_time":33.39373118,"remaining_time":8.244337623},
{"learn":[200884.4278],"iteration":802,"passed_time":33.42390537,"remaining_time":8.19988712},
{"learn":[200879.8999],"iteration":803,"passed_time":33.47654354,"remaining_time":8.160948426},
{"learn":[200879.885],"iteration":804,"passed_time":33.50090398,"remaining_time":8.115125808},
{"learn":[200879.8656],"iteration":805,"passed_time":33.52264987,"remaining_time":8.068727139},
{"learn":[200879.7343],"iteration":806,"passed_time":33.57141361,"remaining_time":8.028851087},
{"learn":[200879.7143],"iteration":807,"passed_time":33.60308986,"remaining_time":7.984892639},
{"learn":[200860.7133],"iteration":808,"passed_time":33.66456566,"remaining_time":7.948000051},
{"learn":[200860.1507],"iteration":809,"passed_time":33.70001256,"remaining_time":7.904941218},
{"learn":[200860.137],"iteration":810,"passed_time":33.73070098,"remaining_time":7.860792212},
{"learn":[200860.1226],"iteration":811,"passed_time":33.76378547,"remaining_time":7.817231118},
{"learn":[200857.7203],"iteration":812,"passed_time":33.8271801,"remaining_time":7.780667503},
{"learn":[200857.7075],"iteration":813,"passed_time":33.84829833,"remaining_time":7.734377751},
{"learn":[200857.2729],"iteration":814,"passed_time":33.88260085,"remaining_time":7.691142524},
{"learn":[200810.8445],"iteration":815,"passed_time":33.93624053,"remaining_time":7.652289531},
{"learn":[200810.8298],"iteration":816,"passed_time":33.96441719,"remaining_time":7.607696873},
{"learn":[200810.7163],"iteration":817,"passed_time":34.02141274,"remaining_time":7.56955638},
{"learn":[200810.7006],"iteration":818,"passed_time":34.05504081,"remaining_time":7.5262056},
{"learn":[200810.0922],"iteration":819,"passed_time":34.09297958,"remaining_time":7.483824787},
{"learn":[200791.8623],"iteration":820,"passed_time":34.14912734,"remaining_time":7.445424841},
{"learn":[200779.6928],"iteration":821,"passed_time":34.20337393,"remaining_time":7.406570024},
{"learn":[200779.6314],"iteration":822,"passed_time":34.25071483,"remaining_time":7.366192619},
{"learn":[200779.0849],"iteration":823,"passed_time":34.3005594,"remaining_time":7.326333075},
{"learn":[200751.296],"iteration":824,"passed_time":34.35480869,"remaining_time":7.287383661},
{"learn":[200748.7625],"iteration":825,"passed_time":34.40671084,"remaining_time":7.247902767},
{"learn":[200748.7426],"iteration":826,"passed_time":34.43144574,"remaining_time":7.202708722},
{"learn":[200748.7233],"iteration":827,"passed_time":34.45746604,"remaining_time":7.157831109},
{"learn":[200748.179],"iteration":828,"passed_time":34.50980485,"remaining_time":7.118427781},
{"learn":[200708.8527],"iteration":829,"passed_time":34.56705636,"remaining_time":7.079999495},
{"learn":[200703.8617],"iteration":830,"passed_time":34.61689147,"remaining_time":7.04001764},
{"learn":[200703.3318],"iteration":831,"passed_time":34.65009779,"remaining_time":6.996654361},
{"learn":[200675.6233],"iteration":832,"passed_time":34.69601399,"remaining_time":6.95586355},
{"learn":[200675.5251],"iteration":833,"passed_time":34.74770366,"remaining_time":6.916209602},
{"learn":[200675.5134],"iteration":834,"passed_time":34.77918418,"remaining_time":6.872533401},
{"learn":[200674.9931],"iteration":835,"passed_time":34.81637971,"remaining_time":6.830007503},
{"learn":[200674.2256],"iteration":836,"passed_time":34.85888434,"remaining_time":6.788528253},
{"learn":[200674.2129],"iteration":837,"passed_time":34.88978975,"remaining_time":6.744804223},
{"learn":[200649.5098],"iteration":838,"passed_time":34.9396747,"remaining_time":6.704752833},
{"learn":[200649.5003],"iteration":839,"passed_time":34.97426852,"remaining_time":6.661765433},
{"learn":[200610.3025],"iteration":840,"passed_time":35.03121119,"remaining_time":6.623023281},
{"learn":[200610.2597],"iteration":841,"passed_time":35.06290881,"remaining_time":6.579500703},
{"learn":[200569.6439],"iteration":842,"passed_time":35.1214894,"remaining_time":6.541012854},
{"learn":[200556.6495],"iteration":843,"passed_time":35.17022626,"remaining_time":6.500657934},
{"learn":[200552.6877],"iteration":844,"passed_time":35.21839577,"remaining_time":6.460179106},
{"learn":[200548.0319],"iteration":845,"passed_time":35.26638656,"remaining_time":6.419649562},
{"learn":[200548.0141],"iteration":846,"passed_time":35.29722544,"remaining_time":6.376004124},
{"learn":[200547.9167],"iteration":847,"passed_time":35.34965543,"remaining_time":6.336258992},
{"learn":[200547.8997],"iteration":848,"passed_time":35.38297005,"remaining_time":6.293084191},
{"learn":[200547.8654],"iteration":849,"passed_time":35.41869614,"remaining_time":6.250358142},
{"learn":[200547.8569],"iteration":850,"passed_time":35.45618205,"remaining_time":6.207956669},
{"learn":[200486.2616],"iteration":851,"passed_time":35.50408957,"remaining_time":6.167377061},
{"learn":[200486.246],"iteration":852,"passed_time":35.54464985,"remaining_time":6.125514101},
{"learn":[200428.4446],"iteration":853,"passed_time":35.60012942,"remaining_time":6.086204796},
{"learn":[200428.4274],"iteration":854,"passed_time":35.62458556,"remaining_time":6.041596382},
{"learn":[200428.4099],"iteration":855,"passed_time":35.65863718,"remaining_time":5.998649245},
{"learn":[200377.2765],"iteration":856,"passed_time":35.70769884,"remaining_time":5.958227461},
{"learn":[200377.2595],"iteration":857,"passed_time":35.73870599,"remaining_time":5.914797494},
{"learn":[200363.0256],"iteration":858,"passed_time":35.78888147,"remaining_time":5.874542825},
{"learn":[200320.9091],"iteration":859,"passed_time":35.8347145,"remaining_time":5.833558174},
{"learn":[200290.5882],"iteration":860,"passed_time":35.89115392,"remaining_time":5.794274559},
{"learn":[200257.749],"iteration":861,"passed_time":35.95184568,"remaining_time":5.755631908},
{"learn":[200251.7127],"iteration":862,"passed_time":36.00243348,"remaining_time":5.715334168},
{"learn":[200251.6908],"iteration":863,"passed_time":36.03051872,"remaining_time":5.67147054},
{"learn":[200251.4342],"iteration":864,"passed_time":36.08668166,"remaining_time":5.632025461},
{"learn":[200248.9887],"iteration":865,"passed_time":36.13041219,"remaining_time":5.590618053},
{"learn":[200248.9676],"iteration":866,"passed_time":36.15736443,"remaining_time":5.546631452},
{"learn":[200248.9299],"iteration":867,"passed_time":36.19035119,"remaining_time":5.503601793},
{"learn":[200247.0779],"iteration":868,"passed_time":36.23679199,"remaining_time":5.462623419},
{"learn":[200246.6264],"iteration":869,"passed_time":36.28607162,"remaining_time":5.422056679},
{"learn":[200246.231],"iteration":870,"passed_time":36.34985956,"remaining_time":5.383618694},
{"learn":[200241.5702],"iteration":871,"passed_time":36.4001717,"remaining_time":5.343144469},
{"learn":[200221.0065],"iteration":872,"passed_time":36.4529167,"remaining_time":5.303001628},
{"learn":[200220.7908],"iteration":873,"passed_time":36.50086304,"remaining_time":5.26213815},
{"learn":[200220.7692],"iteration":874,"passed_time":36.53103853,"remaining_time":5.21871979},
{"learn":[200219.909],"iteration":875,"passed_time":36.57762858,"remaining_time":5.177655187},
{"learn":[200219.0481],"iteration":876,"passed_time":36.6161198,"remaining_time":5.135442116},
{"learn":[200219.011],"iteration":877,"passed_time":36.64870288,"remaining_time":5.092416573},
{"learn":[200214.8291],"iteration":878,"passed_time":36.70000151,"remaining_time":5.051991106},
{"learn":[200214.3206],"iteration":879,"passed_time":36.7437769,"remaining_time":5.010515031},
{"learn":[200214.3007],"iteration":880,"passed_time":36.77384443,"remaining_time":4.967182165},
{"learn":[200214.2817],"iteration":881,"passed_time":36.80098055,"remaining_time":4.923487194},
{"learn":[200205.7933],"iteration":882,"passed_time":36.83896529,"remaining_time":4.881267201},
{"learn":[200205.7537],"iteration":883,"passed_time":36.87492142,"remaining_time":4.838790593},
{"learn":[200199.5813],"iteration":884,"passed_time":36.92151324,"remaining_time":4.79771076},
{"learn":[200194.7765],"iteration":885,"passed_time":36.97401606,"remaining_time":4.757379042},
{"learn":[200194.5766],"iteration":886,"passed_time":37.00922816,"remaining_time":4.714817116},
{"learn":[200194.5565],"iteration":887,"passed_time":37.0355681,"remaining_time":4.671152734},
{"learn":[200194.5234],"iteration":888,"passed_time":37.08268395,"remaining_time":4.630121393},
{"learn":[200194.1578],"iteration":889,"passed_time":37.12598731,"remaining_time":4.588605174},
{"learn":[200193.5543],"iteration":890,"passed_time":37.17127535,"remaining_time":4.547327737},
{"learn":[200191.7711],"iteration":891,"passed_time":37.21676639,"remaining_time":4.506065886},
{"learn":[200191.7508],"iteration":892,"passed_time":37.24567043,"remaining_time":4.462807096},
{"learn":[200170.8182],"iteration":893,"passed_time":37.29950421,"remaining_time":4.422536293},
{"learn":[200170.7846],"iteration":894,"passed_time":37.33547481,"remaining_time":4.380139503},
{"learn":[200166.5173],"iteration":895,"passed_time":37.38417486,"remaining_time":4.339234582},
{"learn":[200158.6865],"iteration":896,"passed_time":37.43771064,"remaining_time":4.298867553},
{"learn":[200158.6692],"iteration":897,"passed_time":37.46499762,"remaining_time":4.255489708},
{"learn":[200158.6535],"iteration":898,"passed_time":37.48929827,"remaining_time":4.211812153},
{"learn":[200156.8561],"iteration":899,"passed_time":37.53353128,"remaining_time":4.170392365},
{"learn":[200143.1374],"iteration":900,"passed_time":37.58753613,"remaining_time":4.130040041},
{"learn":[200143.123],"iteration":901,"passed_time":37.61403639,"remaining_time":4.086669142},
{"learn":[200143.0932],"iteration":902,"passed_time":37.64533968,"remaining_time":4.043851549},
{"learn":[200143.0922],"iteration":903,"passed_time":37.67382338,"remaining_time":4.000760005},
{"learn":[200143.0634],"iteration":904,"passed_time":37.70420928,"remaining_time":3.957900422},
{"learn":[200143.0488],"iteration":905,"passed_time":37.73509214,"remaining_time":3.915119935},
{"learn":[200142.8807],"iteration":906,"passed_time":37.78690455,"remaining_time":3.874511712},
{"learn":[200132.8279],"iteration":907,"passed_time":37.84844877,"remaining_time":3.834864853},
{"learn":[200131.8973],"iteration":908,"passed_time":37.90634007,"remaining_time":3.794804121},
{"learn":[200111.9272],"iteration":909,"passed_time":37.95521935,"remaining_time":3.753812903},
{"learn":[200111.4077],"iteration":910,"passed_time":37.99504516,"remaining_time":3.711919889},
{"learn":[200111.2512],"iteration":911,"passed_time":38.02427727,"remaining_time":3.66900921},
{"learn":[200091.7748],"iteration":912,"passed_time":38.08218261,"remaining_time":3.628860775},
{"learn":[200067.4574],"iteration":913,"passed_time":38.13790529,"remaining_time":3.588468112},
{"learn":[200019.5512],"iteration":914,"passed_time":38.19849472,"remaining_time":3.548494045},
{"learn":[199949.2741],"iteration":915,"passed_time":38.25367608,"remaining_time":3.507979029},
{"learn":[199949.256],"iteration":916,"passed_time":38.28435656,"remaining_time":3.465214388},
{"learn":[199945.2869],"iteration":917,"passed_time":38.32334849,"remaining_time":3.423218493},
{"learn":[199945.2707],"iteration":918,"passed_time":38.35645213,"remaining_time":3.380710144},
{"learn":[199945.0954],"iteration":919,"passed_time":38.40283381,"remaining_time":3.339376853},
{"learn":[199945.079],"iteration":920,"passed_time":38.43645298,"remaining_time":3.296937878},
{"learn":[199945.0784],"iteration":921,"passed_time":38.4757171,"remaining_time":3.25499559},
{"learn":[199945.0627],"iteration":922,"passed_time":38.50254045,"remaining_time":3.212021251},
{"learn":[199943.1889],"iteration":923,"passed_time":38.5690259,"remaining_time":3.172344121},
{"learn":[199930.78],"iteration":924,"passed_time":38.63824247,"remaining_time":3.132830471},
{"learn":[199930.7747],"iteration":925,"passed_time":38.66995428,"remaining_time":3.090255526},
{"learn":[199927.0665],"iteration":926,"passed_time":38.71077786,"remaining_time":3.048421557},
{"learn":[199926.5684],"iteration":927,"passed_time":38.75389201,"remaining_time":3.006767484},
{"learn":[199926.5411],"iteration":928,"passed_time":38.78560992,"remaining_time":2.964239294},
{"learn":[199926.3242],"iteration":929,"passed_time":38.8172133,"remaining_time":2.921725732},
{"learn":[199926.3155],"iteration":930,"passed_time":38.85700171,"remaining_time":2.879842232},
{"learn":[199926.2996],"iteration":931,"passed_time":38.88506188,"remaining_time":2.837107519},
{"learn":[199925.6569],"iteration":932,"passed_time":38.92901481,"remaining_time":2.795545544},
{"learn":[199925.6563],"iteration":933,"passed_time":38.95418382,"remaining_time":2.752651105},
{"learn":[199925.6403],"iteration":934,"passed_time":38.98486363,"remaining_time":2.710177686},
{"learn":[199925.6254],"iteration":935,"passed_time":39.00565067,"remaining_time":2.667053037},
{"learn":[199924.0035],"iteration":936,"passed_time":39.04936411,"remaining_time":2.625517544},
{"learn":[199924.0027],"iteration":937,"passed_time":39.08016388,"remaining_time":2.583123839},
{"learn":[199923.9884],"iteration":938,"passed_time":39.10986014,"remaining_time":2.54068314},
{"learn":[199923.9615],"iteration":939,"passed_time":39.14755334,"remaining_time":2.49878},
{"learn":[199923.9479],"iteration":940,"passed_time":39.17651524,"remaining_time":2.456338362},
{"learn":[199923.9325],"iteration":941,"passed_time":39.21463798,"remaining_time":2.414489387},
{"learn":[199923.932],"iteration":942,"passed_time":39.24102751,"remaining_time":2.371939097},
{"learn":[199923.9189],"iteration":943,"passed_time":39.27312055,"remaining_time":2.329761389},
{"learn":[199923.8928],"iteration":944,"passed_time":39.31042549,"remaining_time":2.287908362},
{"learn":[199923.8925],"iteration":945,"passed_time":39.34332189,"remaining_time":2.2458133},
{"learn":[199923.8621],"iteration":946,"passed_time":39.39251105,"remaining_time":2.20464951},
{"learn":[199923.2383],"iteration":947,"passed_time":39.44129357,"remaining_time":2.163446483},
{"learn":[199923.0393],"iteration":948,"passed_time":39.48603424,"remaining_time":2.12201027},
{"learn":[199923.0271],"iteration":949,"passed_time":39.51259713,"remaining_time":2.079610375},
{"learn":[199923.0135],"iteration":950,"passed_time":39.54282663,"remaining_time":2.037432708},
{"learn":[199904.766],"iteration":951,"passed_time":39.59296833,"remaining_time":1.996284117},
{"learn":[199904.7538],"iteration":952,"passed_time":39.62105849,"remaining_time":1.954029117},
{"learn":[199904.7421],"iteration":953,"passed_time":39.64971636,"remaining_time":1.911831187},
{"learn":[199904.4009],"iteration":954,"passed_time":39.69815629,"remaining_time":1.870593752},
{"learn":[199904.2302],"iteration":955,"passed_time":39.73467693,"remaining_time":1.828792662},
{"learn":[199902.6224],"iteration":956,"passed_time":39.78346006,"remaining_time":1.787553587},
{"learn":[199902.6217],"iteration":957,"passed_time":39.8175182,"remaining_time":1.745653199},
{"learn":[199901.1104],"iteration":958,"passed_time":39.86971751,"remaining_time":1.704544753},
{"learn":[199901.0986],"iteration":959,"passed_time":39.89786405,"remaining_time":1.662411002},
{"learn":[199898.8971],"iteration":960,"passed_time":39.9441607,"remaining_time":1.621042942},
{"learn":[199898.8728],"iteration":961,"passed_time":39.98167903,"remaining_time":1.579317883},
{"learn":[199898.5383],"iteration":962,"passed_time":40.03488012,"remaining_time":1.538204117},
{"learn":[199897.9949],"iteration":963,"passed_time":40.07847258,"remaining_time":1.496706445},
{"learn":[199826.6968],"iteration":964,"passed_time":40.12880025,"remaining_time":1.455448714},
{"learn":[199826.5827],"iteration":965,"passed_time":40.15485662,"remaining_time":1.413317935},
{"learn":[199826.2791],"iteration":966,"passed_time":40.1969055,"remaining_time":1.371766165},
{"learn":[199826.2671],"iteration":967,"passed_time":40.22669338,"remaining_time":1.329808046},
{"learn":[199826.267],"iteration":968,"passed_time":40.24836159,"remaining_time":1.287615283},
{"learn":[199826.2558],"iteration":969,"passed_time":40.27202569,"remaining_time":1.245526568},
{"learn":[199826.2516],"iteration":970,"passed_time":40.30882927,"remaining_time":1.203868228},
{"learn":[199826.1971],"iteration":971,"passed_time":40.35881654,"remaining_time":1.162599653},
{"learn":[199801.7734],"iteration":972,"passed_time":40.40885222,"remaining_time":1.121314502},
{"learn":[199801.4934],"iteration":973,"passed_time":40.4371534,"remaining_time":1.0794312},
{"learn":[199801.4819],"iteration":974,"passed_time":40.46562079,"remaining_time":1.03758002},
{"learn":[199801.4709],"iteration":975,"passed_time":40.49804965,"remaining_time":0.9958536799},
{"learn":[199797.4641],"iteration":976,"passed_time":40.55294921,"remaining_time":0.9546753652},
{"learn":[199797.4514],"iteration":977,"passed_time":40.5849374,"remaining_time":0.912953602},
{"learn":[199797.4392],"iteration":978,"passed_time":40.61135282,"remaining_time":0.8711321851},
{"learn":[199791.5584],"iteration":979,"passed_time":40.6619951,"remaining_time":0.8298366347},
{"learn":[199789.8249],"iteration":980,"passed_time":40.70863424,"remaining_time":0.7884444959},
{"learn":[199789.8103],"iteration":981,"passed_time":40.73973712,"remaining_time":0.7467568923},
{"learn":[199789.7965],"iteration":982,"passed_time":40.76212301,"remaining_time":0.7049400723},
{"learn":[199789.348],"iteration":983,"passed_time":40.79800785,"remaining_time":0.6633822415},
{"learn":[199789.329],"iteration":984,"passed_time":40.82690283,"remaining_time":0.6217294847},
{"learn":[199789.0423],"iteration":985,"passed_time":40.88173142,"remaining_time":0.5804708316},
{"learn":[199789.0287],"iteration":986,"passed_time":40.91622993,"remaining_time":0.5389169089},
{"learn":[199787.2216],"iteration":987,"passed_time":40.96392417,"remaining_time":0.4975375405},
{"learn":[199787.2089],"iteration":988,"passed_time":40.99407672,"remaining_time":0.4559502971},
{"learn":[199787.1887],"iteration":989,"passed_time":41.03543947,"remaining_time":0.4144993886},
{"learn":[199787.1765],"iteration":990,"passed_time":41.06199215,"remaining_time":0.3729141567},
{"learn":[199786.5695],"iteration":991,"passed_time":41.10664015,"remaining_time":0.3315051625},
{"learn":[199786.5576],"iteration":992,"passed_time":41.13788544,"remaining_time":0.2899951642},
{"learn":[199786.5574],"iteration":993,"passed_time":41.16727791,"remaining_time":0.2484946353},
{"learn":[199786.0593],"iteration":994,"passed_time":41.21475394,"remaining_time":0.2071093163},
{"learn":[199777.4695],"iteration":995,"passed_time":41.2768071,"remaining_time":0.1657703096},
{"learn":[199777.3472],"iteration":996,"passed_time":41.31025559,"remaining_time":0.1243036778},
{"learn":[199736.4529],"iteration":997,"passed_time":41.36416995,"remaining_time":0.08289412816},
{"learn":[199687.0945],"iteration":998,"passed_time":41.41542032,"remaining_time":0.0414568772},
{"learn":[199687.0943],"iteration":999,"passed_time":41.44303011,"remaining_time":0}
]}